Workbook

Sheet Paramètres
A1: Paramètres — Démarches SRL (concessionnaire Helicave)
A2: Cellules en bleu sur fond jaune = à modifier. Tous les prix de la grille se recalculent automatiquement.
A4: Réglages généraux
A5: Heures par jour de travail | B5: 8
A6: TVA | B6: 0.21
A7: Remise sur devis | B7: 0
A9: Taux horaires par profil (HT)
A10: Profil | B10: Taux horaire HT | C10: Taux journalier HT
A11: Chef de projet | B11: 75 | C11: =B11*$B$5
A12: Graphiste | B12: 65 | C12: =B12*$B$5
A13: Graphiste 3D | B13: 75 | C13: =B13*$B$5
A14: Photographe | B14: 70 | C14: =B14*$B$5
A15: Vidéaste | B15: 75 | C15: =B15*$B$5
A16: Monteur vidéo | B16: 65 | C16: =B16*$B$5
A17: Pilote drone | B17: 85 | C17: =B17*$B$5
A18: Développeur web | B18: 70 | C18: =B18*$B$5
A19: Community manager | B19: 55 | C19: =B19*$B$5
A20: Rédacteur | B20: 55 | C20: =B20*$B$5
A22: Taux indicatifs (moyenne du marché belge pour une petite agence/indépendant) — à remplacer par vos propres tarifs.

Sheet Grille tarifaire
A1: Grille tarifaire communication — Démarches SRL · Helicave, caves à vin enterrées
A2: Bleu = modifiable (durée, frais, quantité). Remplir la colonne « Qté » pour obtenir un devis en bas de page. Prix en euros.
A4: Réf | B4: Catégorie | C4: Prestation | D4: Profil | E4: Unité | F4: Durée (h) | G4: Durée (jours) | H4: Taux horaire HT | I4: Frais / matériel HT | J4: Prix unitaire HT | K4: Prix unitaire TVAC | L4: Qté | M4: Total HT
A5: Stratégie & gestion de projet
A6: P01 | B6: Stratégie & gestion de projet | C6: Brief & analyse de la demande | D6: Chef de projet | E6: forfait | F6: 4 | G6: =F6/'Paramètres'!$B$5 | H6: =IFERROR(INDEX('Paramètres'!$B$11:$B$20,MATCH(D6,'Paramètres'!$A$11:$A$20,0)),0) | I6: 0 | J6: =F6*H6+I6 | K6: =J6*(1+'Paramètres'!$B$6) | L6: 0 | M6: =J6*L6
A7: P02 | B7: Stratégie & gestion de projet | C7: Stratégie de communication annuelle | D7: Chef de projet | E7: forfait | F7: 16 | G7: =F7/'Paramètres'!$B$5 | H7: =IFERROR(INDEX('Paramètres'!$B$11:$B$20,MATCH(D7,'Paramètres'!$A$11:$A$20,0)),0) | I7: 0 | J7: =F7*H7+I7 | K7: =J7*(1+'Paramètres'!$B$6) | L7: 0 | M7: =J7*L7
A8: P03 | B8: Stratégie & gestion de projet | C8: Réunion client / suivi (déplacement inclus) | D8: Chef de projet | E8: forfait | F8: 2 | G8: =F8/'Paramètres'!$B$5 | H8: =IFERROR(INDEX('Paramètres'!$B$11:$B$20,MATCH(D8,'Paramètres'!$A$11:$A$20,0)),0) | I8: 30 | J8: =F8*H8+I8 | K8: =J8*(1+'Paramètres'!$B$6) | L8: 0 | M8: =J8*L8
A9: P04 | B9: Stratégie & gestion de projet | C9: Gestion de projet | D9: Chef de projet | E9: heure | F9: 1 | G9: =F9/'Paramètres'!$B$5 | H9: =IFERROR(INDEX('Paramètres'!$B$11:$B$20,MATCH(D9,'Paramètres'!$A$11:$A$20,0)),0) | I9: 0 | J9: =F9*H9+I9 | K9: =J9*(1+'Paramètres'!$B$6) | L9: 0 | M9: =J9*L9
A10: Graphisme & print
A11: P05 | B11: Graphisme & print | C11: Heure de graphisme | D11: Graphiste | E11: heure | F11: 1 | G11: =F11/'Paramètres'!$B$5 | H11: =IFERROR(INDEX('Paramètres'!$B$11:$B$20,MATCH(D11,'Paramètres'!$A$11:$A$20,0)),0) | I11: 0 | J11: =F11*H11+I11 | K11: =J11*(1+'Paramètres'!$B$6) | L11: 0 | M11: =J11*L11
A12: P06 | B12: Graphisme & print | C12: Journée de graphisme | D12: Graphiste | E12: jour | F12: 8 | G12: =F12/'Paramètres'!$B$5 | H12: =IFERROR(INDEX('Paramètres'!$B$11:$B$20,MATCH(D12,'Paramètres'!$A$11:$A$20,0)),0) | I12: 0 | J12: =F12*H12+I12 | K12: =J12*(1+'Paramètres'!$B$6) | L12: 0 | M12: =J12*L12
A13: P07 | B13: Graphisme & print | C13: Création / refonte de logo | D13: Graphiste | E13: forfait | F13: 24 | G13: =F13/'Paramètres'!$B$5 | H13: =IFERROR(INDEX('Paramètres'!$B$11:$B$20,MATCH(D13,'Paramètres'!$A$11:$A$20,0)),0) | I13: 0 | J13: =F13*H13+I13 | K13: =J13*(1+'Paramètres'!$B$6) | L13: 0 | M13: =J13*L13
A14: P08 | B14: Graphisme & print | C14: Charte graphique complète | D14: Graphiste | E14: forfait | F14: 16 | G14: =F14/'Paramètres'!$B$5 | H14: =IFERROR(INDEX('Paramètres'!$B$11:$B$20,MATCH(D14,'Paramètres'!$A$11:$A$20,0)),0) | I14: 0 | J14: =F14*H14+I14 | K14: =J14*(1+'Paramètres'!$B$6) | L14: 0 | M14: =J14*L14
A15: P09 | B15: Graphisme & print | C15: Brochure / catalogue Helicave (A4, 8 pages) | D15: Graphiste | E15: forfait | F15: 16 | G15: =F15/'Paramètres'!$B$5 | H15: =IFERROR(INDEX('Paramètres'!$B$11:$B$20,MATCH(D15,'Paramètres'!$A$11:$A$20,0)),0) | I15: 0 | J15: =F15*H15+I15 | K15: =J15*(1+'Paramètres'!$B$6) | L15: 0 | M15: =J15*L15
A16: P10 | B16: Graphisme & print | C16: Flyer A5 recto-verso | D16: Graphiste | E16: forfait | F16: 4 | G16: =F16/'Paramètres'!$B$5 | H16: =IFERROR(INDEX('Paramètres'!$B$11:$B$20,MATCH(D16,'Paramètres'!$A$11:$A$20,0)),0) | I16: 0 | J16: =F16*H16+I16 | K16: =J16*(1+'Paramètres'!$B$6) | L16: 0 | M16: =J16*L16
A17: P11 | B17: Graphisme & print | C17: Affiche / poster | D17: Graphiste | E17: forfait | F17: 4 | G17: =F17/'Paramètres'!$B$5 | H17: =IFERROR(INDEX('Paramètres'!$B$11:$B$20,MATCH(D17,'Paramètres'!$A$11:$A$20,0)),0) | I17: 0 | J17: =F17*H17+I17 | K17: =J17*(1+'Paramètres'!$B$6) | L17: 0 | M17: =J17*L17
A18: P12 | B18: Graphisme & print | C18: Roll-up / kakémono salon | D18: Graphiste | E18: forfait | F18: 4 | G18: =F18/'Paramètres'!$B$5 | H18: =IFERROR(INDEX('Paramètres'!$B$11:$B$20,MATCH(D18,'Paramètres'!$A$11:$A$20,0)),0) | I18: 0 | J18: =F18*H18+I18 | K18: =J18*(1+'Paramètres'!$B$6) | L18: 0 | M18: =J18*L18
A19: P13 | B19: Graphisme & print | C19: Cartes de visite | D19: Graphiste | E19: forfait | F19: 2 | G19: =F19/'Paramètres'!$B$5 | H19: =IFERROR(INDEX('Paramètres'!$B$11:$B$20,MATCH(D19,'Paramètres'!$A$11:$A$20,0)),0) | I19: 0 | J19: =F19*H19+I19 | K19: =J19*(1+'Paramètres'!$B$6) | L19: 0 | M19: =J19*L19
A20: P14 | B20: Graphisme & print | C20: Annonce presse / magazine | D20: Graphiste | E20: forfait | F20: 3 | G20: =F20/'Paramètres'!$B$5 | H20: =IFERROR(INDEX('Paramètres'!$B$11:$B$20,MATCH(D20,'Paramètres'!$A$11:$A$20,0)),0) | I20: 0 | J20: =F20*H20+I20 | K20: =J20*(1+'Paramètres'!$B$6) | L20: 0 | M20: =J20*L20
A21: P15 | B21: Graphisme & print | C21: Habillage véhicule / signalétique | D21: Graphiste | E21: forfait | F21: 8 | G21: =F21/'Paramètres'!$B$5 | H21: =IFERROR(INDEX('Paramètres'!$B$11:$B$20,MATCH(D21,'Paramètres'!$A$11:$A$20,0)),0) | I21: 0 | J21: =F21*H21+I21 | K21: =J21*(1+'Paramètres'!$B$6) | L21: 0 | M21: =J21*L21
A22: P16 | B22: Graphisme & print | C22: Pack 10 visuels réseaux sociaux | D22: Graphiste | E22: forfait | F22: 6 | G22: =F22/'Paramètres'!$B$5 | H22: =IFERROR(INDEX('Paramètres'!$B$11:$B$20,MATCH(D22,'Paramètres'!$A$11:$A$20,0)),0) | I22: 0 | J22: =F22*H22+I22 | K22: =J22*(1+'Paramètres'!$B$6) | L22: 0 | M22: =J22*L22
... A24: P18 | B24: Graphisme & print | C24: Modélisation 3D / rendu d'une cave Helicave | D24: Graphiste 3D | E24: forfait | F24: 16 | G24: =F24/'Paramètres'!$B$5 | H24: =IFERROR(INDEX('Paramètres'!$B$11:$B$20,MATCH(D24,'Paramètres'!$A$11:$A$20,0)),0) | I24: 0 | J24: =F24*H24+I24 | K24: =J24*(1+'Paramètres'!$B$6) | L24: 0 | M24: =J24*L24
A25: Photo (shooting)
A26: P19 | B26: Photo (shooting) | C26: Shooting photo demi-journée | D26: Photographe | E26: demi-journée | F26: 4 | G26: =F26/'Paramètres'!$B$5 | H26: =IFERROR(INDEX('Paramètres'!$B$11:$B$20,MATCH(D26,'Paramètres'!$A$11:$A$20,0)),0) | I26: 50 | J26: =F26*H26+I26 | K26: =J26*(1+'Paramètres'!$B$6) | L26: 0 | M26: =J26*L26
A27: P20 | B27: Photo (shooting) | C27: Shooting photo journée | D27: Photographe | E27: jour | F27: 8 | G27: =F27/'Paramètres'!$B$5 | H27: =IFERROR(INDEX('Paramètres'!$B$11:$B$20,MATCH(D27,'Paramètres'!$A$11:$A$20,0)),0) | I27: 80 | J27: =F27*H27+I27 | K27: =J27*(1+'Paramètres'!$B$6) | L27: 0 | M27: =J27*L27
A28: P21 | B28: Photo (shooting) | C28: Reportage chantier (avant / pendant / après pose) | D28: Photographe | E28: forfait | F28: 6 | G28: =F28/'Paramètres'!$B$5 | H28: =IFERROR(INDEX('Paramètres'!$B$11:$B$20,MATCH(D28,'Paramètres'!$A$11:$A$20,0)),0) | I28: 50 | J28: =F28*H28+I28 | K28: =J28*(1+'Paramètres'!$B$6) | L28: 0 | M28: =J28*L28
A29: P22 | B29: Photo (shooting) | C29: Couverture photo événement / portes ouvertes | D29: Photographe | E29: forfait | F29: 4 | G29: =F29/'Paramètres'!$B$5 | H29: =IFERROR(INDEX('Paramètres'!$B$11:$B$20,MATCH(D29,'Paramètres'!$A$11:$A$20,0)),0) | I29: 50 | J29: =F29*H29+I29 | K29: =J29*(1+'Paramètres'!$B$6) | L29: 0 | M29: =J29*L29
A30: P23 | B30: Photo (shooting) | C30: Retouche photo (par photo) | D30: Photographe | E30: photo | F30: 0.25 | G30: =F30/'Paramètres'!$B$5 | H30: =IFERROR(INDEX('Paramètres'!$B$11:$B$20,MATCH(D30,'Paramètres'!$A$11:$A$20,0)),0) | I30: 0 | J30: =F30*H30+I30 | K30: =J30*(1+'Paramètres'!$B$6) | L30: 0 | M30: =J30*L30
A31: Vidéo (tournage & montage)
A32: P24 | B32: Vidéo (tournage & montage) | C32: Tournage demi-journée (matériel inclus) | D32: Vidéaste | E32: demi-journée | F32: 4 | G32: =F32/'Paramètres'!$B$5 | H32: =IFERROR(INDEX('Paramètres'!$B$11:$B$20,MATCH(D32,'Paramètres'!$A$11:$A$20,0)),0) | I32: 100 | J32: =F32*H32+I32 | K32: =J32*(1+'Paramètres'!$B$6) | L32: 0 | M32: =J32*L32
A33: P25 | B33: Vidéo (tournage & montage) | C33: Tournage journée (matériel inclus) | D33: Vidéaste | E33: jour | F33: 8 | G33: =F33/'Paramètres'!$B$5 | H33: =IFERROR(INDEX('Paramètres'!$B$11:$B$20,MATCH(D33,'Paramètres'!$A$11:$A$20,0)),0) | I33: 150 | J33: =F33*H33+I33 | K33: =J33*(1+'Paramètres'!$B$6) | L33: 1 | M33: =J33*L33
A34: P26 | B34: Vidéo (tournage & montage) | C34: Prises de vue drone | D34: Pilote drone | E34: demi-journée | F34: 4 | G34: =F34/'Paramètres'!$B$5 | H34: =IFERROR(INDEX('Paramètres'!$B$11:$B$20,MATCH(D34,'Paramètres'!$A$11:$A$20,0)),0) | I34: 150 | J34: =F34*H34+I34 | K34: =J34*(1+'Paramètres'!$B$6) | L34: 0 | M34: =J34*L34
A35: P27 | B35: Vidéo (tournage & montage) | C35: Heure de montage | D35: Monteur vidéo | E35: heure | F35: 1 | G35: =F35/'Paramètres'!$B$5 | H35: =IFERROR(INDEX('Paramètres'!$B$11:$B$20,MATCH(D35,'Paramètres'!$A$11:$A$20,0)),0) | I35: 0 | J35: =F35*H35+I35 | K35: =J35*(1+'Paramètres'!$B$6) | L35: 0 | M35: =J35*L35
A36: P28 | B36: Vidéo (tournage & montage) | C36: Montage film promo Helicave (1–2 min) | D36: Monteur vidéo | E36: forfait | F36: 16 | G36: =F36/'Paramètres'!$B$5 | H36: =IFERROR(INDEX('Paramètres'!$B$11:$B$20,MATCH(D36,'Paramètres'!$A$11:$A$20,0)),0) | I36: 0 | J36: =F36*H36+I36 | K36: =J36*(1+'Paramètres'!$B$6) | L36: 1 | M36: =J36*L36
A37: P29 | B37: Vidéo (tournage & montage) | C37: Montage vidéo témoignage client | D37: Monteur vidéo | E37: forfait | F37: 8 | G37: =F37/'Paramètres'!$B$5 | H37: =IFERROR(INDEX('Paramètres'!$B$11:$B$20,MATCH(D37,'Paramètres'!$A$11:$A$20,0)),0) | I37: 0 | J37: =F37*H37+I37 | K37: =J37*(1+'Paramètres'!$B$6) | L37: 0 | M37: =J37*L37
A38: P30 | B38: Vidéo (tournage & montage) | C38: Réel / short réseaux sociaux (≤ 60 s) | D38: Monteur vidéo | E38: forfait | F38: 3 | G38: =F38/'Paramètres'!$B$5 | H38: =IFERROR(INDEX('Paramètres'!$B$11:$B$20,MATCH(D38,'Paramètres'!$A$11:$A$20,0)),0) | I38: 0 | J38: =F38*H38+I38 | K38: =J38*(1+'Paramètres'!$B$6) | L38: 0 | M38: =J38*L38
A39: P31 | B39: Vidéo (tournage & montage) | C39: Motion design / animation 3D d'installation | D39: Graphiste 3D | E39: forfait | F39: 16 | G39: =F39/'Paramètres'!$B$5 | H39: =IFERROR(INDEX('Paramètres'!$B$11:$B$20,MATCH(D39,'Paramètres'!$A$11:$A$20,0)),0) | I39: 0 | J39: =F39*H39+I39 | K39: =J39*(1+'Paramètres'!$B$6) | L39: 0 | M39: =J39*L39
A40: P32 | B40: Vidéo (tournage & montage) | C40: Sous-titrage | D40: Monteur vidéo | E40: forfait | F40: 2 | G40: =F40/'Paramètres'!$B$5 | H40: =IFERROR(INDEX('Paramètres'!$B$11:$B$20,MATCH(D40,'Paramètres'!$A$11:$A$20,0)),0) | I40: 0 | J40: =F40*H40+I40 | K40: =J40*(1+'Paramètres'!$B$6) | L40: 0 | M40: =J40*L40
A41: P33 | B41: Vidéo (tournage & montage) | C41: Voix off professionnelle | D41: Monteur vidéo | E41: forfait | F41: 1 | G41: =F41/'Paramètres'!$B$5 | H41: =IFERROR(INDEX('Paramètres'!$B$11:$B$20,MATCH(D41,'Paramètres'!$A$11:$A$20,0)),0) | I41: 150 | J41: =F41*H41+I41 | K41: =J41*(1+'Paramètres'!$B$6) | L41: 0 | M41: =J41*L41
A42: P34 | B42: Vidéo (tournage & montage) | C42: Musique sous licence | D42: Monteur vidéo | E42: forfait | F42: 0 | G42: =F42/'Paramètres'!$B$5 | H42: =IFERROR(INDEX('Paramètres'!$B$11:$B$20,MATCH(D42,'Paramètres'!$A$11:$A$20,0)),0) | I42: 50 | J42: =F42*H42+I42 | K42: =J42*(1+'Paramètres'!$B$6) | L42: 0 | M42: =J42*L42
A43: Web & hébergement
A44: P35 | B44: Web & hébergement | C44: Site vitrine (5–7 pages) | D44: Développeur web | E44: forfait | F44: 40 | G44: =F44/'Paramètres'!$B$5 | H44: =IFERROR(INDEX('Paramètres'!$B$11:$B$20,MATCH(D44,'Paramètres'!$A$11:$A$20,0)),0) | I44: 0 | J44: =F44*H44+I44 | K44: =J44*(1+'Paramètres'!$B$6) | L44: 0 | M44: =J44*L44
A45: P36 | B45: Web & hébergement | C45: Landing page / page promo | D45: Développeur web | E45: forfait | F45: 12 | G45: =F45/'Paramètres'!$B$5 | H45: =IFERROR(INDEX('Paramètres'!$B$11:$B$20,MATCH(D45,'Paramètres'!$A$11:$A$20,0)),0) | I45: 0 | J45: =F45*H45+I45 | K45: =J45*(1+'Paramètres'!$B$6) | L45: 0 | M45: =J45*L45
A46: P37 | B46: Web & hébergement | C46: Rédaction d'une page web | D46: Rédacteur | E46: forfait | F46: 2 | G46: =F46/'Paramètres'!$B$5 | H46: =IFERROR(INDEX('Paramètres'!$B$11:$B$20,MATCH(D46,'Paramètres'!$A$11:$A$20,0)),0) | I46: 0 | J46: =F46*H46+I46 | K46: =J46*(1+'Paramètres'!$B$6) | L46: 0 | M46: =J46*L46
A47: P38 | B47: Web & hébergement | C47: Audit & optimisation SEO | D47: Développeur web | E47: forfait | F47: 8 | G47: =F47/'Paramètres'!$B$5 | H47: =IFERROR(INDEX('Paramètres'!$B$11:$B$20,MATCH(D47,'Paramètres'!$A$11:$A$20,0)),0) | I47: 0 | J47: =F47*H47+I47 | K47: =J47*(1+'Paramètres'!$B$6) | L47: 0 | M47: =J47*L47
A48: P39 | B48: Web & hébergement | C48: Maintenance & mises à jour | D48: Développeur web | E48: mois | F48: 2 | G48: =F48/'Paramètres'!$B$5 | H48: =IFERROR(INDEX('Paramètres'!$B$11:$B$20,MATCH(D48,'Paramètres'!$A$11:$A$20,0)),0) | I48: 0 | J48: =F48*H48+I48 | K48: =J48*(1+'Paramètres'!$B$6) | L48: 0 | M48: =J48*L48
A49: P40 | B49: Web & hébergement | C49: Hébergement web | D49: Développeur web | E49: an | F49: 0 | G49: =F49/'Paramètres'!$B$5 | H49: =IFERROR(INDEX('Paramètres'!$B$11:$B$20,MATCH(D49,'Paramètres'!$A$11:$A$20,0)),0) | I49: 180 | J49: =F49*H49+I49 | K49: =J49*(1+'Paramètres'!$B$6) | L49: 0 | M49: =J49*L49
A50: P41 | B50: Web & hébergement | C50: Nom de domaine | D50: Développeur web | E50: an | F50: 0 | G50: =F50/'Paramètres'!$B$5 | H50: =IFERROR(INDEX('Paramètres'!$B$11:$B$20,MATCH(D50,'Paramètres'!$A$11:$A$20,0)),0) | I50: 25 | J50: =F50*H50+I50 | K50: =J50*(1+'Paramètres'!$B$6) | L50: 0 | M50: =J50*L50
A51: P42 | B51: Web & hébergement | C51: Adresses e-mail professionnelles | D51: Développeur web | E51: an | F51: 0 | G51: =F51/'Paramètres'!$B$5 | H51: =IFERROR(INDEX('Paramètres'!$B$11:$B$20,MATCH(D51,'Paramètres'!$A$11:$A$20,0)),0) | I51: 60 | J51: =F51*H51+I51 | K51: =J51*(1+'Paramètres'!$B$6) | L51: 0 | M51: =J51*L51
A52: Réseaux sociaux & marketing
A53: P43 | B53: Réseaux sociaux & marketing | C53: Gestion réseaux sociaux (8 posts / mois) | D53: Community manager | E53: mois | F53: 16 | G53: =F53/'Paramètres'!$B$5 | H53: =IFERROR(INDEX('Paramètres'!$B$11:$B$20,MATCH(D53,'Paramètres'!$A$11:$A$20,0)),0) | I53: 0 | J53: =F53*H53+I53 | K53: =J53*(1+'Paramètres'!$B$6) | L53: 0 | M53: =J53*L53
A54: P44 | B54: Réseaux sociaux & marketing | C54: Création d'une publication | D54: Community manager | E54: forfait | F54: 1 | G54: =F54/'Paramètres'!$B$5 | H54: =IFERROR(INDEX('Paramètres'!$B$11:$B$20,MATCH(D54,'Paramètres'!$A$11:$A$20,0)),0) | I54: 0 | J54: =F54*H54+I54 | K54: =J54*(1+'Paramètres'!$B$6) | L54: 0 | M54: =J54*L54
A55: P45 | B55: Réseaux sociaux & marketing | C55: Mise en place campagne pub Meta / Google | D55: Community manager | E55: forfait | F55: 6 | G55: =F55/'Paramètres'!$B$5 | H55: =IFERROR(INDEX('Paramètres'!$B$11:$B$20,MATCH(D55,'Paramètres'!$A$11:$A$20,0)),0) | I55: 0 | J55: =F55*H55+I55 | K55: =J55*(1+'Paramètres'!$B$6) | L55: 0 | M55: =J55*L55
A56: P46 | B56: Réseaux sociaux & marketing | C56: Gestion campagne publicitaire (hors budget pub) | D56: Community manager | E56: mois | F56: 4 | G56: =F56/'Paramètres'!$B$5 | H56: =IFERROR(INDEX('Paramètres'!$B$11:$B$20,MATCH(D56,'Paramètres'!$A$11:$A$20,0)),0) | I56: 0 | J56: =F56*H56+I56 | K56: =J56*(1+'Paramètres'!$B$6) | L56: 0 | M56: =J56*L56
A57: P47 | B57: Réseaux sociaux & marketing | C57: Newsletter / e-mailing | D57: Community manager | E57: forfait | F57: 4 | G57: =F57/'Paramètres'!$B$5 | H57: =IFERROR(INDEX('Paramètres'!$B$11:$B$20,MATCH(D57,'Paramètres'!$A$11:$A$20,0)),0) | I57: 0 | J57: =F57*H57+I57 | K57: =J57*(1+'Paramètres'!$B$6) | L57: 0 | M57: =J57*L57
A58: P48 | B58: Réseaux sociaux & marketing | C58: Article de blog / communiqué de presse | D58: Rédacteur | E58: forfait | F58: 3 | G58: =F58/'Paramètres'!$B$5 | H58: =IFERROR(INDEX('Paramètres'!$B$11:$B$20,MATCH(D58,'Paramètres'!$A$11:$A$20,0)),0) | I58: 0 | J58: =F58*H58+I58 | K58: =J58*(1+'Paramètres'!$B$6) | L58: 0 | M58: =J58*L58
K60: Exemple de devis (Qté) :
K61: Sous-total HT | M61: =SUM(M5:M58)
K62: Remise | M62: =-M61*'Paramètres'!$B$7
K63: Total HT après remise | M63: =M61+M62
K64: TVA | M64: =M63*'Paramètres'!$B$6
K65: Total TVAC | M65: =M63+M64
K66: Temps total (heures) | M66: =SUMPRODUCT(F5:F58,L5:L58)
K67: Temps total (jours) | M67: =M66/'Paramètres'!$B$5
A69: Prix indicatifs HT hors impression, hors budget publicitaire, frais de déplacement hors Belgique en supplément. Prix unitaire = Durée (h) × Taux horaire du profil + Frais/matériel.

Sheet Récap par catégorie
A1: Récapitulatif du devis par catégorie
A3: Catégorie | B3: Heures | C3: Jours | D3: Total HT | E3: Total TVAC
A4: Stratégie & gestion de projet | B4: =SUMPRODUCT(('Grille tarifaire'!$B$5:$B$58=A4)*'Grille tarifaire'!$F$5:$F$58*'Grille tarifaire'!$L$5:$L$58) | C4: =B4/'Paramètres'!$B$5 | D4: =SUMIFS('Grille tarifaire'!$M$5:$M$58,'Grille tarifaire'!$B$5:$B$58,A4) | E4: =D4*(1+'Paramètres'!$B$6)
A5: Graphisme & print | B5: =SUMPRODUCT(('Grille tarifaire'!$B$5:$B$58=A5)*'Grille tarifaire'!$F$5:$F$58*'Grille tarifaire'!$L$5:$L$58) | C5: =B5/'Paramètres'!$B$5 | D5: =SUMIFS('Grille tarifaire'!$M$5:$M$58,'Grille tarifaire'!$B$5:$B$58,A5) | E5: =D5*(1+'Paramètres'!$B$6)
A6: Photo (shooting) | B6: =SUMPRODUCT(('Grille tarifaire'!$B$5:$B$58=A6)*'Grille tarifaire'!$F$5:$F$58*'Grille tarifaire'!$L$5:$L$58) | C6: =B6/'Paramètres'!$B$5 | D6: =SUMIFS('Grille tarifaire'!$M$5:$M$58,'Grille tarifaire'!$B$5:$B$58,A6) | E6: =D6*(1+'Paramètres'!$B$6)
A7: Vidéo (tournage & montage) | B7: =SUMPRODUCT(('Grille tarifaire'!$B$5:$B$58=A7)*'Grille tarifaire'!$F$5:$F$58*'Grille tarifaire'!$L$5:$L$58) | C7: =B7/'Paramètres'!$B$5 | D7: =SUMIFS('Grille tarifaire'!$M$5:$M$58,'Grille tarifaire'!$B$5:$B$58,A7) | E7: =D7*(1+'Paramètres'!$B$6)
A8: Web & hébergement | B8: =SUMPRODUCT(('Grille tarifaire'!$B$5:$B$58=A8)*'Grille tarifaire'!$F$5:$F$58*'Grille tarifaire'!$L$5:$L$58) | C8: =B8/'Paramètres'!$B$5 | D8: =SUMIFS('Grille tarifaire'!$M$5:$M$58,'Grille tarifaire'!$B$5:$B$58,A8) | E8: =D8*(1+'Paramètres'!$B$6)
A9: Réseaux sociaux & marketing | B9: =SUMPRODUCT(('Grille tarifaire'!$B$5:$B$58=A9)*'Grille tarifaire'!$F$5:$F$58*'Grille tarifaire'!$L$5:$L$58) | C9: =B9/'Paramètres'!$B$5 | D9: =SUMIFS('Grille tarifaire'!$M$5:$M$58,'Grille tarifaire'!$B$5:$B$58,A9) | E9: =D9*(1+'Paramètres'!$B$6)
A10: Total (avant remise) | B10: =SUM(B4:B9) | C10: =SUM(C4:C9) | D10: =SUM(D4:D9) | E10: =SUM(E4:E9)
