Workbook

Sheet Price list
B2: ='Paramètres'!C5
B3: PRICE LIST — COMMUNICATION, DIRECTION ARTISTIQUE & DESIGN
B4: ='Paramètres'!C6
B7: PRÉPARÉ POUR | L7: DATE | M7: VALIDITÉ
B8: ='Paramètres'!C7 | L8: ='Paramètres'!C8 | M8: ='Paramètres'!C9&" jours"
B10: Cochez la colonne « VALIDÉ » pour chaque prestation retenue : le montant engagé et le cumul se calculent automatiquement.
B11: ="Durées indicatives en heures et en jours/homme (1 j/h = "&'Paramètres'!C10&" h). Prix HT, TVA "&TEXT('Paramètres'!C11,"0%")&"."
B13: RÉF. | C13: PRESTATION | D13: DÉTAIL / LIVRABLES | E13: UNITÉ | F13: HEURES | G13: J/H | H13: PRIX HT | I13: PRIX TTC | J13: QTÉ | K13: VALIDÉ | L13: MONTANT ENGAGÉ HT | M13: CUMUL ENGAGÉ HT
B15: 01 | C15: STRATÉGIE & DIRECTION ARTISTIQUE
B16: 01.01 | C16: Audit de communication & de marque | D16: Analyse de l'existant, concurrence, recommandations | E16: forfait | F16: 12 | G16: =IF(F16="","",F16/'Paramètres'!$C$10) | H16: 1224 | I16: =H16*(1+'Paramètres'!$C$11) | J16: 1 | K16: FALSE | L16: =IF(K16=TRUE,H16*J16,0) | M16: =SUM(L$14:L16)
B17: 01.02 | C17: Plateforme de marque | D17: Positionnement, valeurs, ton, cibles, messages clés | E17: forfait | F17: 24 | G17: =IF(F17="","",F17/'Paramètres'!$C$10) | H17: 2448 | I17: =H17*(1+'Paramètres'!$C$11) | J17: 1 | K17: FALSE | L17: =IF(K17=TRUE,H17*J17,0) | M17: =SUM(L$14:L17)
B18: 01.03 | C18: Stratégie de communication annuelle | D18: Plan d'actions, canaux, calendrier, budget | E18: forfait | F18: 24 | G18: =IF(F18="","",F18/'Paramètres'!$C$10) | H18: 2016 | I18: =H18*(1+'Paramètres'!$C$11) | J18: 1 | K18: FALSE | L18: =IF(K18=TRUE,H18*J18,0) | M18: =SUM(L$14:L18)
B19: 01.04 | C19: Atelier créatif / brainstorming | D19: Séance de travail avec vos équipes (½ journée) | E19: forfait | F19: 4 | G19: =IF(F19="","",F19/'Paramètres'!$C$10) | H19: 408 | I19: =H19*(1+'Paramètres'!$C$11) | J19: 1 | K19: FALSE | L19: =IF(K19=TRUE,H19*J19,0) | M19: =SUM(L$14:L19)
B20: 01.05 | C20: Moodboard & concept créatif | D20: Pistes visuelles et univers graphique | E20: forfait | F20: 8 | G20: =IF(F20="","",F20/'Paramètres'!$C$10) | H20: 816 | I20: =H20*(1+'Paramètres'!$C$11) | J20: 1 | K20: FALSE | L20: =IF(K20=TRUE,H20*J20,0) | M20: =SUM(L$14:L20)
B21: 01.06 | C21: Direction artistique | D21: Supervision créative d'un projet | E21: heure | F21: 1 | G21: =IF(F21="","",F21/'Paramètres'!$C$10) | H21: 102 | I21: =H21*(1+'Paramètres'!$C$11) | J21: 1 | K21: FALSE | L21: =IF(K21=TRUE,H21*J21,0) | M21: =SUM(L$14:L21)
B22: 01.07 | C22: Direction artistique — journée | D22: Présence shooting / tournage / production | E22: jour | F22: 8 | G22: =IF(F22="","",F22/'Paramètres'!$C$10) | H22: 816 | I22: =H22*(1+'Paramètres'!$C$11) | J22: 1 | K22: FALSE | L22: =IF(K22=TRUE,H22*J22,0) | M22: =SUM(L$14:L22)
B23: 01.08 | C23: Gestion de projet | D23: Coordination, planning, suivi fournisseurs | E23: heure | F23: 1 | G23: =IF(F23="","",F23/'Paramètres'!$C$10) | H23: 84 | I23: =H23*(1+'Paramètres'!$C$11) | J23: 1 | K23: FALSE | L23: =IF(K23=TRUE,H23*J23,0) | M23: =SUM(L$14:L23)
B24: 01.09 | C24: Réunion client | D24: Rendez-vous de suivi, déplacement local inclus | E24: forfait | F24: 2 | G24: =IF(F24="","",F24/'Paramètres'!$C$10) | H24: 204 | I24: =H24*(1+'Paramètres'!$C$11) | J24: 1 | K24: FALSE | L24: =IF(K24=TRUE,H24*J24,0) | M24: =SUM(L$14:L24)
B26: 02 | C26: IDENTITÉ VISUELLE & BRANDING
B27: 02.01 | C27: Création de logo | D27: 3 pistes créatives, 2 allers-retours, fichiers sources | E27: forfait | F27: 24 | G27: =IF(F27="","",F27/'Paramètres'!$C$10) | H27: 1872 | I27: =H27*(1+'Paramètres'!$C$11) | J27: 1 | K27: FALSE | L27: =IF(K27=TRUE,H27*J27,0) | M27: =SUM(L$14:L27)
B28: 02.02 | C28: Refonte / modernisation de logo | D28: Évolution d'un logo existant | E28: forfait | F28: 14 | G28: =IF(F28="","",F28/'Paramètres'!$C$10) | H28: 1092 | I28: =H28*(1+'Paramètres'!$C$11) | J28: 1 | K28: FALSE | L28: =IF(K28=TRUE,H28*J28,0) | M28: =SUM(L$14:L28)
B29: 02.03 | C29: Charte graphique | D29: Couleurs, typographies, règles d'usage (PDF) | E29: forfait | F29: 16 | G29: =IF(F29="","",F29/'Paramètres'!$C$10) | H29: 1248 | I29: =H29*(1+'Paramètres'!$C$11) | J29: 1 | K29: FALSE | L29: =IF(K29=TRUE,H29*J29,0) | M29: =SUM(L$14:L29)
B30: 02.04 | C30: Brandbook complet | D30: Charte + déclinaisons + exemples d'application | E30: forfait | F30: 32 | G30: =IF(F30="","",F30/'Paramètres'!$C$10) | H30: 3264 | I30: =H30*(1+'Paramètres'!$C$11) | J30: 1 | K30: FALSE | L30: =IF(K30=TRUE,H30*J30,0) | M30: =SUM(L$14:L30)
B31: 02.05 | C31: Naming | D31: Recherche de nom, 10 propositions argumentées | E31: forfait | F31: 12 | G31: =IF(F31="","",F31/'Paramètres'!$C$10) | H31: 792 | I31: =H31*(1+'Paramètres'!$C$11) | J31: 1 | K31: FALSE | L31: =IF(K31=TRUE,H31*J31,0) | M31: =SUM(L$14:L31)
B32: 02.06 | C32: Slogan / signature de marque | D32: 5 propositions | E32: forfait | F32: 4 | G32: =IF(F32="","",F32/'Paramètres'!$C$10) | H32: 264 | I32: =H32*(1+'Paramètres'!$C$11) | J32: 1 | K32: FALSE | L32: =IF(K32=TRUE,H32*J32,0) | M32: =SUM(L$14:L32)
B33: 02.07 | C33: Papeterie | D33: Carte de visite, papier en-tête, enveloppe | E33: forfait | F33: 6 | G33: =IF(F33="","",F33/'Paramètres'!$C$10) | H33: 468 | I33: =H33*(1+'Paramètres'!$C$11) | J33: 1 | K33: FALSE | L33: =IF(K33=TRUE,H33*J33,0) | M33: =SUM(L$14:L33)
B34: 02.08 | C34: Signature e-mail HTML | D34: Modèle aux couleurs de la marque | E34: forfait | F34: 2 | G34: =IF(F34="","",F34/'Paramètres'!$C$10) | H34: 156 | I34: =H34*(1+'Paramètres'!$C$11) | J34: 1 | K34: FALSE | L34: =IF(K34=TRUE,H34*J34,0) | M34: =SUM(L$14:L34)
B35: 02.09 | C35: Templates Office / PowerPoint | D35: Modèles Word + présentation | E35: forfait | F35: 8 | G35: =IF(F35="","",F35/'Paramètres'!$C$10) | H35: 624 | I35: =H35*(1+'Paramètres'!$C$11) | J35: 1 | K35: FALSE | L35: =IF(K35=TRUE,H35*J35,0) | M35: =SUM(L$14:L35)
B37: 03 | C37: GRAPHISME PRINT & ÉDITION
B38: 03.01 | C38: Heure de graphisme | D38: Création ou adaptation graphique | E38: heure | F38: 1 | G38: =IF(F38="","",F38/'Paramètres'!$C$10) | H38: 78 | I38: =H38*(1+'Paramètres'!$C$11) | J38: 1 | K38: FALSE | L38: =IF(K38=TRUE,H38*J38,0) | M38: =SUM(L$14:L38)
B39: 03.02 | C39: Journée de graphisme | D39: Journée de création (1 j/h) | E39: jour | F39: 8 | G39: =IF(F39="","",F39/'Paramètres'!$C$10) | H39: 624 | I39: =H39*(1+'Paramètres'!$C$11) | J39: 1 | K39: FALSE | L39: =IF(K39=TRUE,H39*J39,0) | M39: =SUM(L$14:L39)
B40: 03.03 | C40: Flyer A5 / A4 | D40: Recto-verso, fichiers prêts à imprimer | E40: forfait | F40: 4 | G40: =IF(F40="","",F40/'Paramètres'!$C$10) | H40: 312 | I40: =H40*(1+'Paramètres'!$C$11) | J40: 1 | K40: FALSE | L40: =IF(K40=TRUE,H40*J40,0) | M40: =SUM(L$14:L40)
B41: 03.04 | C41: Dépliant 3 volets | D41: Mise en page complète | E41: forfait | F41: 8 | G41: =IF(F41="","",F41/'Paramètres'!$C$10) | H41: 624 | I41: =H41*(1+'Paramètres'!$C$11) | J41: 1 | K41: FALSE | L41: =IF(K41=TRUE,H41*J41,0) | M41: =SUM(L$14:L41)
B42: 03.05 | C42: Brochure 8 pages | D42: Conception + mise en page | E42: forfait | F42: 16 | G42: =IF(F42="","",F42/'Paramètres'!$C$10) | H42: 1248 | I42: =H42*(1+'Paramètres'!$C$11) | J42: 1 | K42: FALSE | L42: =IF(K42=TRUE,H42*J42,0) | M42: =SUM(L$14:L42)
B43: 03.06 | C43: Catalogue / brochure — par page | D43: Mise en page, au-delà de 8 pages | E43: page | F43: 1.5 | G43: =IF(F43="","",F43/'Paramètres'!$C$10) | H43: 120 | I43: =H43*(1+'Paramètres'!$C$11) | J43: 1 | K43: FALSE | L43: =IF(K43=TRUE,H43*J43,0) | M43: =SUM(L$14:L43)
B44: 03.07 | C44: Affiche / poster | D44: Tout format | E44: forfait | F44: 4 | G44: =IF(F44="","",F44/'Paramètres'!$C$10) | H44: 312 | I44: =H44*(1+'Paramètres'!$C$11) | J44: 1 | K44: FALSE | L44: =IF(K44=TRUE,H44*J44,0) | M44: =SUM(L$14:L44)
B45: 03.08 | C45: Roll-up / kakémono | D45: Format standard 85 × 200 cm | E45: forfait | F45: 4 | G45: =IF(F45="","",F45/'Paramètres'!$C$10) | H45: 312 | I45: =H45*(1+'Paramètres'!$C$11) | J45: 1 | K45: FALSE | L45: =IF(K45=TRUE,H45*J45,0) | M45: =SUM(L$14:L45)
B46: 03.09 | C46: Bâche / banderole | D46: Grand format | E46: forfait | F46: 3 | G46: =IF(F46="","",F46/'Paramètres'!$C$10) | H46: 234 | I46: =H46*(1+'Paramètres'!$C$11) | J46: 1 | K46: FALSE | L46: =IF(K46=TRUE,H46*J46,0) | M46: =SUM(L$14:L46)
B47: 03.10 | C47: Annonce presse / magazine | D47: Création + déclinaisons formats | E47: forfait | F47: 3 | G47: =IF(F47="","",F47/'Paramètres'!$C$10) | H47: 234 | I47: =H47*(1+'Paramètres'!$C$11) | J47: 1 | K47: FALSE | L47: =IF(K47=TRUE,H47*J47,0) | M47: =SUM(L$14:L47)
B48: 03.11 | C48: Carton d'invitation | D48: Événement, portes ouvertes | E48: forfait | F48: 3 | G48: =IF(F48="","",F48/'Paramètres'!$C$10) | H48: 234 | I48: =H48*(1+'Paramètres'!$C$11) | J48: 1 | K48: FALSE | L48: =IF(K48=TRUE,H48*J48,0) | M48: =SUM(L$14:L48)
B49: 03.12 | C49: Packaging / étiquette | D49: Création d'un design de packaging | E49: forfait | F49: 16 | G49: =IF(F49="","",F49/'Paramètres'!$C$10) | H49: 1248 | I49: =H49*(1+'Paramètres'!$C$11) | J49: 1 | K49: FALSE | L49: =IF(K49=TRUE,H49*J49,0) | M49: =SUM(L$14:L49)
B50: 03.13 | C50: Déclinaison / adaptation de format | D50: Adaptation d'un visuel existant | E50: forfait | F50: 1 | G50: =IF(F50="","",F50/'Paramètres'!$C$10) | H50: 78 | I50: =H50*(1+'Paramètres'!$C$11) | J50: 1 | K50: FALSE | L50: =IF(K50=TRUE,H50*J50,0) | M50: =SUM(L$14:L50)
B52: 04 | C52: SIGNALÉTIQUE, SALONS & ÉVÉNEMENTIEL
B53: 04.01 | C53: Stand salon / foire | D53: Conception graphique du stand | E53: forfait | F53: 16 | G53: =IF(F53="","",F53/'Paramètres'!$C$10) | H53: 1248 | I53: =H53*(1+'Paramètres'!$C$11) | J53: 1 | K53: FALSE | L53: =IF(K53=TRUE,H53*J53,0) | M53: =SUM(L$14:L53)
B54: 04.02 | C54: Habillage véhicule | D54: Utilitaire ou voiture de service | E54: forfait | F54: 8 | G54: =IF(F54="","",F54/'Paramètres'!$C$10) | H54: 624 | I54: =H54*(1+'Paramètres'!$C$11) | J54: 1 | K54: FALSE | L54: =IF(K54=TRUE,H54*J54,0) | M54: =SUM(L$14:L54)
B55: 04.03 | C55: Vitrine / enseigne | D55: Design de façade ou vitrophanie | E55: forfait | F55: 6 | G55: =IF(F55="","",F55/'Paramètres'!$C$10) | H55: 468 | I55: =H55*(1+'Paramètres'!$C$11) | J55: 1 | K55: FALSE | L55: =IF(K55=TRUE,H55*J55,0) | M55: =SUM(L$14:L55)
B56: 04.04 | C56: Signalétique intérieure / showroom | D56: Panneaux, directionnel, PLV | E56: forfait | F56: 8 | G56: =IF(F56="","",F56/'Paramètres'!$C$10) | H56: 624 | I56: =H56*(1+'Paramètres'!$C$11) | J56: 1 | K56: FALSE | L56: =IF(K56=TRUE,H56*J56,0) | M56: =SUM(L$14:L56)
B57: 04.05 | C57: PLV / présentoir | D57: Présentoir comptoir ou sol | E57: forfait | F57: 6 | G57: =IF(F57="","",F57/'Paramètres'!$C$10) | H57: 468 | I57: =H57*(1+'Paramètres'!$C$11) | J57: 1 | K57: FALSE | L57: =IF(K57=TRUE,H57*J57,0) | M57: =SUM(L$14:L57)
B59: 05 | C59: ILLUSTRATION, 3D & INFOGRAPHIE
B60: 05.01 | C60: Illustration simple | D60: Pictogramme élaboré, dessin au trait | E60: forfait | F60: 3 | G60: =IF(F60="","",F60/'Paramètres'!$C$10) | H60: 234 | I60: =H60*(1+'Paramètres'!$C$11) | J60: 1 | K60: FALSE | L60: =IF(K60=TRUE,H60*J60,0) | M60: =SUM(L$14:L60)
B61: 05.02 | C61: Illustration détaillée | D61: Illustration couleur complexe | E61: forfait | F61: 10 | G61: =IF(F61="","",F61/'Paramètres'!$C$10) | H61: 780 | I61: =H61*(1+'Paramètres'!$C$11) | J61: 1 | K61: FALSE | L61: =IF(K61=TRUE,H61*J61,0) | M61: =SUM(L$14:L61)
B62: 05.03 | C62: Pack de 10 pictogrammes | D62: Set d'icônes cohérent | E62: forfait | F62: 8 | G62: =IF(F62="","",F62/'Paramètres'!$C$10) | H62: 624 | I62: =H62*(1+'Paramètres'!$C$11) | J62: 1 | K62: FALSE | L62: =IF(K62=TRUE,H62*J62,0) | M62: =SUM(L$14:L62)
B63: 05.04 | C63: Infographie | D63: Schéma, données, processus | E63: forfait | F63: 6 | G63: =IF(F63="","",F63/'Paramètres'!$C$10) | H63: 468 | I63: =H63*(1+'Paramètres'!$C$11) | J63: 1 | K63: FALSE | L63: =IF(K63=TRUE,H63*J63,0) | M63: =SUM(L$14:L63)
B64: 05.05 | C64: Modélisation 3D & rendu | D64: Modèle 3D + 3 rendus photoréalistes | E64: forfait | F64: 16 | G64: =IF(F64="","",F64/'Paramètres'!$C$10) | H64: 1440 | I64: =H64*(1+'Paramètres'!$C$11) | J64: 1 | K64: FALSE | L64: =IF(K64=TRUE,H64*J64,0) | M64: =SUM(L$14:L64)
B65: 05.06 | C65: Mockups / mises en situation | D65: 3 visuels de présentation | E65: forfait | F65: 2 | G65: =IF(F65="","",F65/'Paramètres'!$C$10) | H65: 156 | I65: =H65*(1+'Paramètres'!$C$11) | J65: 1 | K65: FALSE | L65: =IF(K65=TRUE,H65*J65,0) | M65: =SUM(L$14:L65)
B67: 06 | C67: PHOTOGRAPHIE
B68: 06.01 | C68: Shooting photo — demi-journée | D68: 4 h sur site, 20 photos sélectionnées en HD, matériel inclus | E68: demi-journée | F68: 4 | G68: =IF(F68="","",F68/'Paramètres'!$C$10) | H68: 396 | I68: =H68*(1+'Paramètres'!$C$11) | J68: 1 | K68: FALSE | L68: =IF(K68=TRUE,H68*J68,0) | M68: =SUM(L$14:L68)
B69: 06.02 | C69: Shooting photo — journée | D69: 8 h sur site, 40 photos sélectionnées en HD, matériel inclus | E69: jour | F69: 8 | G69: =IF(F69="","",F69/'Paramètres'!$C$10) | H69: 768 | I69: =H69*(1+'Paramètres'!$C$11) | J69: 1 | K69: FALSE | L69: =IF(K69=TRUE,H69*J69,0) | M69: =SUM(L$14:L69)
B70: 06.03 | C70: Packshot produit — par photo | D70: Fond blanc ou mise en scène | E70: photo | F70: 0.5 | G70: =IF(F70="","",F70/'Paramètres'!$C$10) | H70: 42 | I70: =H70*(1+'Paramètres'!$C$11) | J70: 1 | K70: FALSE | L70: =IF(K70=TRUE,H70*J70,0) | M70: =SUM(L$14:L70)
B71: 06.04 | C71: Portraits corporate | D71: Équipe / dirigeants, jusqu'à 10 personnes | E71: forfait | F71: 4 | G71: =IF(F71="","",F71/'Paramètres'!$C$10) | H71: 396 | I71: =H71*(1+'Paramètres'!$C$11) | J71: 1 | K71: FALSE | L71: =IF(K71=TRUE,H71*J71,0) | M71: =SUM(L$14:L71)
B72: 06.05 | C72: Reportage événement / chantier | D72: Couverture 4 h, sélection livrée en HD | E72: forfait | F72: 5 | G72: =IF(F72="","",F72/'Paramètres'!$C$10) | H72: 480 | I72: =H72*(1+'Paramètres'!$C$11) | J72: 1 | K72: FALSE | L72: =IF(K72=TRUE,H72*J72,0) | M72: =SUM(L$14:L72)
B73: 06.06 | C73: Photo aérienne par drone | D73: Demi-journée, pilote certifié | E73: demi-journée | F73: 4 | G73: =IF(F73="","",F73/'Paramètres'!$C$10) | H73: 588 | I73: =H73*(1+'Paramètres'!$C$11) | J73: 1 | K73: FALSE | L73: =IF(K73=TRUE,H73*J73,0) | M73: =SUM(L$14:L73)
B75: 07 | C75: VIDÉO & MOTION DESIGN
B76: 07.01 | C76: Tournage — demi-journée | D76: Vidéaste + matériel (caméra, son, lumière) | E76: demi-journée | F76: 4 | G76: =IF(F76="","",F76/'Paramètres'!$C$10) | H76: 480 | I76: =H76*(1+'Paramètres'!$C$11) | J76: 1 | K76: FALSE | L76: =IF(K76=TRUE,H76*J76,0) | M76: =SUM(L$14:L76)
B77: 07.02 | C77: Tournage — journée | D77: Vidéaste + matériel (caméra, son, lumière) | E77: jour | F77: 8 | G77: =IF(F77="","",F77/'Paramètres'!$C$10) | H77: 900 | I77: =H77*(1+'Paramètres'!$C$11) | J77: 1 | K77: FALSE | L77: =IF(K77=TRUE,H77*J77,0) | M77: =SUM(L$14:L77)
B78: 07.03 | C78: Prises de vue drone | D78: Demi-journée, pilote certifié | E78: demi-journée | F78: 4 | G78: =IF(F78="","",F78/'Paramètres'!$C$10) | H78: 588 | I78: =H78*(1+'Paramètres'!$C$11) | J78: 1 | K78: FALSE | L78: =IF(K78=TRUE,H78*J78,0) | M78: =SUM(L$14:L78)
B79: 07.04 | C79: Heure de montage | D79: Montage, étalonnage, mixage | E79: heure | F79: 1 | G79: =IF(F79="","",F79/'Paramètres'!$C$10) | H79: 84 | I79: =H79*(1+'Paramètres'!$C$11) | J79: 1 | K79: FALSE | L79: =IF(K79=TRUE,H79*J79,0) | M79: =SUM(L$14:L79)
B80: 07.05 | C80: Film de présentation 1–2 min | D80: Montage complet, 2 allers-retours | E80: forfait | F80: 16 | G80: =IF(F80="","",F80/'Paramètres'!$C$10) | H80: 1344 | I80: =H80*(1+'Paramètres'!$C$11) | J80: 1 | K80: FALSE | L80: =IF(K80=TRUE,H80*J80,0) | M80: =SUM(L$14:L80)
B81: 07.06 | C81: Vidéo témoignage client | D81: Interview montée, 1–2 min | E81: forfait | F81: 8 | G81: =IF(F81="","",F81/'Paramètres'!$C$10) | H81: 672 | I81: =H81*(1+'Paramètres'!$C$11) | J81: 1 | K81: FALSE | L81: =IF(K81=TRUE,H81*J81,0) | M81: =SUM(L$14:L81)
B82: 07.07 | C82: Réel / short réseaux sociaux | D82: Format vertical ≤ 60 s | E82: forfait | F82: 3 | G82: =IF(F82="","",F82/'Paramètres'!$C$10) | H82: 252 | I82: =H82*(1+'Paramètres'!$C$11) | J82: 1 | K82: FALSE | L82: =IF(K82=TRUE,H82*J82,0) | M82: =SUM(L$14:L82)
B83: 07.08 | C83: Motion design 30 s | D83: Animation 2D, script et storyboard inclus | E83: forfait | F83: 24 | G83: =IF(F83="","",F83/'Paramètres'!$C$10) | H83: 2016 | I83: =H83*(1+'Paramètres'!$C$11) | J83: 1 | K83: FALSE | L83: =IF(K83=TRUE,H83*J83,0) | M83: =SUM(L$14:L83)
B84: 07.09 | C84: Animation de logo | D84: Logo animé (intro / outro) | E84: forfait | F84: 6 | G84: =IF(F84="","",F84/'Paramètres'!$C$10) | H84: 504 | I84: =H84*(1+'Paramètres'!$C$11) | J84: 1 | K84: FALSE | L84: =IF(K84=TRUE,H84*J84,0) | M84: =SUM(L$14:L84)
B85: 07.10 | C85: Animation 3D | D85: Visualisation produit / installation | E85: forfait | F85: 24 | G85: =IF(F85="","",F85/'Paramètres'!$C$10) | H85: 2160 | I85: =H85*(1+'Paramètres'!$C$11) | J85: 1 | K85: FALSE | L85: =IF(K85=TRUE,H85*J85,0) | M85: =SUM(L$14:L85)
B86: 07.11 | C86: Sous-titrage | D86: Par vidéo, 1 langue | E86: forfait | F86: 2 | G86: =IF(F86="","",F86/'Paramètres'!$C$10) | H86: 168 | I86: =H86*(1+'Paramètres'!$C$11) | J86: 1 | K86: FALSE | L86: =IF(K86=TRUE,H86*J86,0) | M86: =SUM(L$14:L86)
B87: 07.12 | C87: Voix off professionnelle | D87: Comédien voix, 1 langue | E87: forfait | F87: 1 | G87: =IF(F87="","",F87/'Paramètres'!$C$10) | H87: 264 | I87: =H87*(1+'Paramètres'!$C$11) | J87: 1 | K87: FALSE | L87: =IF(K87=TRUE,H87*J87,0) | M87: =SUM(L$14:L87)
B88: 07.13 | C88: Musique sous licence | D88: Droits d'utilisation web | E88: forfait | G88: =IF(F88="","",F88/'Paramètres'!$C$10) | H88: 60 | I88: =H88*(1+'Paramètres'!$C$11) | J88: 1 | K88: FALSE | L88: =IF(K88=TRUE,H88*J88,0) | M88: =SUM(L$14:L88)
B90: 08 | C90: WEB & DIGITAL
B91: 08.01 | C91: Webdesign UI/UX — par page | D91: Maquette desktop + mobile | E91: page | F91: 6 | G91: =IF(F91="","",F91/'Paramètres'!$C$10) | H91: 504 | I91: =H91*(1+'Paramètres'!$C$11) | J91: 1 | K91: FALSE | L91: =IF(K91=TRUE,H91*J91,0) | M91: =SUM(L$14:L91)
B92: 08.02 | C92: Site vitrine (5–7 pages) | D92: Design + développement WordPress, responsive | E92: forfait | F92: 48 | G92: =IF(F92="","",F92/'Paramètres'!$C$10) | H92: 4032 | I92: =H92*(1+'Paramètres'!$C$11) | J92: 1 | K92: FALSE | L92: =IF(K92=TRUE,H92*J92,0) | M92: =SUM(L$14:L92)
B93: 08.03 | C93: Site e-commerce | D93: Boutique en ligne, paiement, jusqu'à 50 produits | E93: forfait | F93: 100 | G93: =IF(F93="","",F93/'Paramètres'!$C$10) | H93: 8400 | I93: =H93*(1+'Paramètres'!$C$11) | J93: 1 | K93: FALSE | L93: =IF(K93=TRUE,H93*J93,0) | M93: =SUM(L$14:L93)
B94: 08.04 | C94: Landing page | D94: Page promotionnelle / campagne | E94: forfait | F94: 12 | G94: =IF(F94="","",F94/'Paramètres'!$C$10) | H94: 1008 | I94: =H94*(1+'Paramètres'!$C$11) | J94: 1 | K94: FALSE | L94: =IF(K94=TRUE,H94*J94,0) | M94: =SUM(L$14:L94)
B95: 08.05 | C95: Rédaction web — par page | D95: Textes optimisés SEO | E95: page | F95: 2 | G95: =IF(F95="","",F95/'Paramètres'!$C$10) | H95: 132 | I95: =H95*(1+'Paramètres'!$C$11) | J95: 1 | K95: FALSE | L95: =IF(K95=TRUE,H95*J95,0) | M95: =SUM(L$14:L95)
B96: 08.06 | C96: Audit & optimisation SEO | D96: Analyse technique + recommandations | E96: forfait | F96: 10 | G96: =IF(F96="","",F96/'Paramètres'!$C$10) | H96: 840 | I96: =H96*(1+'Paramètres'!$C$11) | J96: 1 | K96: FALSE | L96: =IF(K96=TRUE,H96*J96,0) | M96: =SUM(L$14:L96)
B97: 08.07 | C97: Template newsletter | D97: Modèle e-mailing responsive | E97: forfait | F97: 6 | G97: =IF(F97="","",F97/'Paramètres'!$C$10) | H97: 504 | I97: =H97*(1+'Paramètres'!$C$11) | J97: 1 | K97: FALSE | L97: =IF(K97=TRUE,H97*J97,0) | M97: =SUM(L$14:L97)
B98: 08.08 | C98: Formation back-office | D98: Prise en main du site (2 h) | E98: forfait | F98: 2 | G98: =IF(F98="","",F98/'Paramètres'!$C$10) | H98: 168 | I98: =H98*(1+'Paramètres'!$C$11) | J98: 1 | K98: FALSE | L98: =IF(K98=TRUE,H98*J98,0) | M98: =SUM(L$14:L98)
B99: 08.09 | C99: Maintenance & mises à jour | D99: Sécurité, sauvegardes, petites modifications | E99: mois | F99: 2 | G99: =IF(F99="","",F99/'Paramètres'!$C$10) | H99: 168 | I99: =H99*(1+'Paramètres'!$C$11) | J99: 1 | K99: FALSE | L99: =IF(K99=TRUE,H99*J99,0) | M99: =SUM(L$14:L99)
B100: 08.10 | C100: Hébergement web | D100: Hébergement + certificat SSL | E100: an | G100: =IF(F100="","",F100/'Paramètres'!$C$10) | H100: 216 | I100: =H100*(1+'Paramètres'!$C$11) | J100: 1 | K100: FALSE | L100: =IF(K100=TRUE,H100*J100,0) | M100: =SUM(L$14:L100)
B101: 08.11 | C101: Nom de domaine | D101: Enregistrement / renouvellement | E101: an | G101: =IF(F101="","",F101/'Paramètres'!$C$10) | H101: 30 | I101: =H101*(1+'Paramètres'!$C$11) | J101: 1 | K101: FALSE | L101: =IF(K101=TRUE,H101*J101,0) | M101: =SUM(L$14:L101)
B103: 09 | C103: RÉSEAUX SOCIAUX & CONTENU
B104: 09.01 | C104: Stratégie social media | D104: Audit, ligne éditoriale, calendrier | E104: forfait | F104: 12 | G104: =IF(F104="","",F104/'Paramètres'!$C$10) | H104: 792 | I104: =H104*(1+'Paramètres'!$C$11) | J104: 1 | K104: FALSE | L104: =IF(K104=TRUE,H104*J104,0) | M104: =SUM(L$14:L104)
B105: 09.02 | C105: Création / optimisation des comptes | D105: Facebook, Instagram, LinkedIn | E105: forfait | F105: 4 | G105: =IF(F105="","",F105/'Paramètres'!$C$10) | H105: 264 | I105: =H105*(1+'Paramètres'!$C$11) | J105: 1 | K105: FALSE | L105: =IF(K105=TRUE,H105*J105,0) | M105: =SUM(L$14:L105)
B106: 09.03 | C106: Gestion réseaux sociaux | D106: 8 publications / mois + modération | E106: mois | F106: 16 | G106: =IF(F106="","",F106/'Paramètres'!$C$10) | H106: 1056 | I106: =H106*(1+'Paramètres'!$C$11) | J106: 1 | K106: FALSE | L106: =IF(K106=TRUE,H106*J106,0) | M106: =SUM(L$14:L106)
B107: 09.04 | C107: Pack 10 visuels réseaux sociaux | D107: Templates aux couleurs de la marque | E107: forfait | F107: 6 | G107: =IF(F107="","",F107/'Paramètres'!$C$10) | H107: 468 | I107: =H107*(1+'Paramètres'!$C$11) | J107: 1 | K107: FALSE | L107: =IF(K107=TRUE,H107*J107,0) | M107: =SUM(L$14:L107)
B108: 09.05 | C108: Campagne publicitaire — mise en place | D108: Meta / Google Ads, ciblage, visuels | E108: forfait | F108: 6 | G108: =IF(F108="","",F108/'Paramètres'!$C$10) | H108: 396 | I108: =H108*(1+'Paramètres'!$C$11) | J108: 1 | K108: FALSE | L108: =IF(K108=TRUE,H108*J108,0) | M108: =SUM(L$14:L108)
B109: 09.06 | C109: Campagne publicitaire — gestion | D109: Suivi et optimisation (hors budget média) | E109: mois | F109: 4 | G109: =IF(F109="","",F109/'Paramètres'!$C$10) | H109: 264 | I109: =H109*(1+'Paramètres'!$C$11) | J109: 1 | K109: FALSE | L109: =IF(K109=TRUE,H109*J109,0) | M109: =SUM(L$14:L109)
B110: 09.07 | C110: Newsletter / e-mailing | D110: Rédaction + mise en page + envoi | E110: forfait | F110: 4 | G110: =IF(F110="","",F110/'Paramètres'!$C$10) | H110: 264 | I110: =H110*(1+'Paramètres'!$C$11) | J110: 1 | K110: FALSE | L110: =IF(K110=TRUE,H110*J110,0) | M110: =SUM(L$14:L110)
B111: 09.08 | C111: Article de blog | D111: 800 à 1 000 mots, optimisé SEO | E111: forfait | F111: 3 | G111: =IF(F111="","",F111/'Paramètres'!$C$10) | H111: 198 | I111: =H111*(1+'Paramètres'!$C$11) | J111: 1 | K111: FALSE | L111: =IF(K111=TRUE,H111*J111,0) | M111: =SUM(L$14:L111)
B112: 09.09 | C112: Communiqué de presse | D112: Rédaction + liste de diffusion | E112: forfait | F112: 4 | G112: =IF(F112="","",F112/'Paramètres'!$C$10) | H112: 264 | I112: =H112*(1+'Paramètres'!$C$11) | J112: 1 | K112: FALSE | L112: =IF(K112=TRUE,H112*J112,0) | M112: =SUM(L$14:L112)
B113: 09.10 | C113: Rapport de performance | D113: Statistiques mensuelles commentées | E113: mois | F113: 2 | G113: =IF(F113="","",F113/'Paramètres'!$C$10) | H113: 132 | I113: =H113*(1+'Paramètres'!$C$11) | J113: 1 | K113: FALSE | L113: =IF(K113=TRUE,H113*J113,0) | M113: =SUM(L$14:L113)
B115: 10 | C115: PRODUCTION & IMPRESSION
...

Sheet Paramètres
B2: PARAMÈTRES
B3: Cellules en bleu sur fond jaune = modifiables. La price list se met à jour automatiquement.
B5: Agence | C5: FABRIZIO VERRECCHIA — ABYSSE.LAB (18H22)
B6: Contact | C6: fab@18h22.com · SIRET 893 142 356 00037
B7: Client | C7: Démarches SRL — concessionnaire Helicave
B8: Date | C8: 46288
B9: Validité de l'offre (jours) | C9: 90
B10: Heures par jour (1 j/h) | C10: 8
B11: TVA | C11: 0.2 | D11: TVA française 20 %. Client belge assujetti : mettre 0 % (autoliquidation, art. 283-2 CGI).
