Workbook

Sheet Price list
B2: ='Paramètres'!C5
B3: PRICE LIST — COMMUNICATION, DIRECTION ARTISTIQUE & DESIGN
B4: ='Paramètres'!C6
B7: PRÉPARÉ POUR | H7: DATE | I7: VALIDITÉ
B8: ='Paramètres'!C7 | H8: ='Paramètres'!C8 | I8: ='Paramètres'!C9&" jours"
B10: NOS TAUX HORAIRES & JOURNALIERS | E10: ="1 j/h (jour/homme) = "&'Paramètres'!C10&" heures de travail"
B11: PROFIL | H11: € / HEURE HT | I11: € / JOUR HT
B12: ='Paramètres'!B17 | H12: ='Paramètres'!C17 | I12: ='Paramètres'!D17
B13: ='Paramètres'!B18 | H13: ='Paramètres'!C18 | I13: ='Paramètres'!D18
B14: ='Paramètres'!B19 | H14: ='Paramètres'!C19 | I14: ='Paramètres'!D19
B15: ='Paramètres'!B20 | H15: ='Paramètres'!C20 | I15: ='Paramètres'!D20
B16: ='Paramètres'!B21 | H16: ='Paramètres'!C21 | I16: ='Paramètres'!D21
B17: ='Paramètres'!B22 | H17: ='Paramètres'!C22 | I17: ='Paramètres'!D22
B18: ='Paramètres'!B23 | H18: ='Paramètres'!C23 | I18: ='Paramètres'!D23
B19: ='Paramètres'!B24 | H19: ='Paramètres'!C24 | I19: ='Paramètres'!D24
B20: ='Paramètres'!B25 | H20: ='Paramètres'!C25 | I20: ='Paramètres'!D25
B21: ='Paramètres'!B26 | H21: ='Paramètres'!C26 | I21: ='Paramètres'!D26
B22: ='Paramètres'!B27 | H22: ='Paramètres'!C27 | I22: ='Paramètres'!D27
B23: ='Paramètres'!B28 | H23: ='Paramètres'!C28 | I23: ='Paramètres'!D28
B24: ='Paramètres'!B29 | H24: ='Paramètres'!C29 | I24: ='Paramètres'!D29
B27: NOS PRESTATIONS | E27: Durées indicatives en heures et en jours/homme (j/h).
B28: RÉF. | C28: PRESTATION | D28: DÉTAIL / LIVRABLES | E28: UNITÉ | F28: HEURES | G28: J/H | H28: PRIX HT | I28: PRIX TVAC | K28: Profil (interne) | L28: Frais HT (interne) | M28: Taux (interne)
B30: 01 | C30: STRATÉGIE & DIRECTION ARTISTIQUE
B31: 01.01 | C31: Audit de communication & de marque | D31: Analyse de l'existant, concurrence, recommandations | E31: forfait | F31: 12 | G31: =IF(F31="","",F31/'Paramètres'!$C$10) | H31: =CEILING(N(F31)*M31+L31,'Paramètres'!$C$12) | I31: =H31*(1+'Paramètres'!$C$11) | K31: Directeur artistique | L31: 0 | M31: =IFERROR(INDEX('Paramètres'!$C$17:$C$29,MATCH(K31,'Paramètres'!$B$17:$B$29,0)),0)
B32: 01.02 | C32: Plateforme de marque | D32: Positionnement, valeurs, ton, cibles, messages clés | E32: forfait | F32: 24 | G32: =IF(F32="","",F32/'Paramètres'!$C$10) | H32: =CEILING(N(F32)*M32+L32,'Paramètres'!$C$12) | I32: =H32*(1+'Paramètres'!$C$11) | K32: Directeur artistique | L32: 0 | M32: =IFERROR(INDEX('Paramètres'!$C$17:$C$29,MATCH(K32,'Paramètres'!$B$17:$B$29,0)),0)
B33: 01.03 | C33: Stratégie de communication annuelle | D33: Plan d'actions, canaux, calendrier, budget | E33: forfait | F33: 24 | G33: =IF(F33="","",F33/'Paramètres'!$C$10) | H33: =CEILING(N(F33)*M33+L33,'Paramètres'!$C$12) | I33: =H33*(1+'Paramètres'!$C$11) | K33: Chef de projet | L33: 0 | M33: =IFERROR(INDEX('Paramètres'!$C$17:$C$29,MATCH(K33,'Paramètres'!$B$17:$B$29,0)),0)
B34: 01.04 | C34: Atelier créatif / brainstorming | D34: Séance de travail avec vos équipes (½ journée) | E34: forfait | F34: 4 | G34: =IF(F34="","",F34/'Paramètres'!$C$10) | H34: =CEILING(N(F34)*M34+L34,'Paramètres'!$C$12) | I34: =H34*(1+'Paramètres'!$C$11) | K34: Directeur artistique | L34: 0 | M34: =IFERROR(INDEX('Paramètres'!$C$17:$C$29,MATCH(K34,'Paramètres'!$B$17:$B$29,0)),0)
B35: 01.05 | C35: Moodboard & concept créatif | D35: Pistes visuelles et univers graphique | E35: forfait | F35: 8 | G35: =IF(F35="","",F35/'Paramètres'!$C$10) | H35: =CEILING(N(F35)*M35+L35,'Paramètres'!$C$12) | I35: =H35*(1+'Paramètres'!$C$11) | K35: Directeur artistique | L35: 0 | M35: =IFERROR(INDEX('Paramètres'!$C$17:$C$29,MATCH(K35,'Paramètres'!$B$17:$B$29,0)),0)
B36: 01.06 | C36: Direction artistique | D36: Supervision créative d'un projet | E36: heure | F36: 1 | G36: =IF(F36="","",F36/'Paramètres'!$C$10) | H36: =CEILING(N(F36)*M36+L36,'Paramètres'!$C$12) | I36: =H36*(1+'Paramètres'!$C$11) | K36: Directeur artistique | L36: 0 | M36: =IFERROR(INDEX('Paramètres'!$C$17:$C$29,MATCH(K36,'Paramètres'!$B$17:$B$29,0)),0)
B37: 01.07 | C37: Direction artistique — journée | D37: Présence shooting / tournage / production | E37: jour | F37: 8 | G37: =IF(F37="","",F37/'Paramètres'!$C$10) | H37: =CEILING(N(F37)*M37+L37,'Paramètres'!$C$12) | I37: =H37*(1+'Paramètres'!$C$11) | K37: Directeur artistique | L37: 0 | M37: =IFERROR(INDEX('Paramètres'!$C$17:$C$29,MATCH(K37,'Paramètres'!$B$17:$B$29,0)),0)
B38: 01.08 | C38: Gestion de projet | D38: Coordination, planning, suivi fournisseurs | E38: heure | F38: 1 | G38: =IF(F38="","",F38/'Paramètres'!$C$10) | H38: =CEILING(N(F38)*M38+L38,'Paramètres'!$C$12) | I38: =H38*(1+'Paramètres'!$C$11) | K38: Chef de projet | L38: 0 | M38: =IFERROR(INDEX('Paramètres'!$C$17:$C$29,MATCH(K38,'Paramètres'!$B$17:$B$29,0)),0)
B39: 01.09 | C39: Réunion client | D39: Rendez-vous de suivi, déplacement inclus (Belgique) | E39: forfait | F39: 2 | G39: =IF(F39="","",F39/'Paramètres'!$C$10) | H39: =CEILING(N(F39)*M39+L39,'Paramètres'!$C$12) | I39: =H39*(1+'Paramètres'!$C$11) | K39: Chef de projet | L39: 30 | M39: =IFERROR(INDEX('Paramètres'!$C$17:$C$29,MATCH(K39,'Paramètres'!$B$17:$B$29,0)),0)
B41: 02 | C41: IDENTITÉ VISUELLE & BRANDING
B42: 02.01 | C42: Création de logo | D42: 3 pistes créatives, 2 allers-retours, fichiers sources | E42: forfait | F42: 24 | G42: =IF(F42="","",F42/'Paramètres'!$C$10) | H42: =CEILING(N(F42)*M42+L42,'Paramètres'!$C$12) | I42: =H42*(1+'Paramètres'!$C$11) | K42: Graphiste | L42: 0 | M42: =IFERROR(INDEX('Paramètres'!$C$17:$C$29,MATCH(K42,'Paramètres'!$B$17:$B$29,0)),0)
B43: 02.02 | C43: Refonte / modernisation de logo | D43: Évolution d'un logo existant | E43: forfait | F43: 14 | G43: =IF(F43="","",F43/'Paramètres'!$C$10) | H43: =CEILING(N(F43)*M43+L43,'Paramètres'!$C$12) | I43: =H43*(1+'Paramètres'!$C$11) | K43: Graphiste | L43: 0 | M43: =IFERROR(INDEX('Paramètres'!$C$17:$C$29,MATCH(K43,'Paramètres'!$B$17:$B$29,0)),0)
B44: 02.03 | C44: Charte graphique | D44: Couleurs, typographies, règles d'usage (PDF) | E44: forfait | F44: 16 | G44: =IF(F44="","",F44/'Paramètres'!$C$10) | H44: =CEILING(N(F44)*M44+L44,'Paramètres'!$C$12) | I44: =H44*(1+'Paramètres'!$C$11) | K44: Graphiste | L44: 0 | M44: =IFERROR(INDEX('Paramètres'!$C$17:$C$29,MATCH(K44,'Paramètres'!$B$17:$B$29,0)),0)
B45: 02.04 | C45: Brandbook complet | D45: Charte + déclinaisons + exemples d'application | E45: forfait | F45: 32 | G45: =IF(F45="","",F45/'Paramètres'!$C$10) | H45: =CEILING(N(F45)*M45+L45,'Paramètres'!$C$12) | I45: =H45*(1+'Paramètres'!$C$11) | K45: Directeur artistique | L45: 0 | M45: =IFERROR(INDEX('Paramètres'!$C$17:$C$29,MATCH(K45,'Paramètres'!$B$17:$B$29,0)),0)
B46: 02.05 | C46: Naming | D46: Recherche de nom, 10 propositions argumentées | E46: forfait | F46: 12 | G46: =IF(F46="","",F46/'Paramètres'!$C$10) | H46: =CEILING(N(F46)*M46+L46,'Paramètres'!$C$12) | I46: =H46*(1+'Paramètres'!$C$11) | K46: Rédacteur / copywriter | L46: 0 | M46: =IFERROR(INDEX('Paramètres'!$C$17:$C$29,MATCH(K46,'Paramètres'!$B$17:$B$29,0)),0)
B47: 02.06 | C47: Slogan / signature de marque | D47: 5 propositions | E47: forfait | F47: 4 | G47: =IF(F47="","",F47/'Paramètres'!$C$10) | H47: =CEILING(N(F47)*M47+L47,'Paramètres'!$C$12) | I47: =H47*(1+'Paramètres'!$C$11) | K47: Rédacteur / copywriter | L47: 0 | M47: =IFERROR(INDEX('Paramètres'!$C$17:$C$29,MATCH(K47,'Paramètres'!$B$17:$B$29,0)),0)
B48: 02.07 | C48: Papeterie | D48: Carte de visite, papier en-tête, enveloppe | E48: forfait | F48: 6 | G48: =IF(F48="","",F48/'Paramètres'!$C$10) | H48: =CEILING(N(F48)*M48+L48,'Paramètres'!$C$12) | I48: =H48*(1+'Paramètres'!$C$11) | K48: Graphiste | L48: 0 | M48: =IFERROR(INDEX('Paramètres'!$C$17:$C$29,MATCH(K48,'Paramètres'!$B$17:$B$29,0)),0)
B49: 02.08 | C49: Signature e-mail HTML | D49: Modèle aux couleurs de la marque | E49: forfait | F49: 2 | G49: =IF(F49="","",F49/'Paramètres'!$C$10) | H49: =CEILING(N(F49)*M49+L49,'Paramètres'!$C$12) | I49: =H49*(1+'Paramètres'!$C$11) | K49: Graphiste | L49: 0 | M49: =IFERROR(INDEX('Paramètres'!$C$17:$C$29,MATCH(K49,'Paramètres'!$B$17:$B$29,0)),0)
B50: 02.09 | C50: Templates Office / PowerPoint | D50: Modèles Word + présentation | E50: forfait | F50: 8 | G50: =IF(F50="","",F50/'Paramètres'!$C$10) | H50: =CEILING(N(F50)*M50+L50,'Paramètres'!$C$12) | I50: =H50*(1+'Paramètres'!$C$11) | K50: Graphiste | L50: 0 | M50: =IFERROR(INDEX('Paramètres'!$C$17:$C$29,MATCH(K50,'Paramètres'!$B$17:$B$29,0)),0)
B52: 03 | C52: GRAPHISME PRINT & ÉDITION
B53: 03.01 | C53: Heure de graphisme | D53: Création ou adaptation graphique | E53: heure | F53: 1 | G53: =IF(F53="","",F53/'Paramètres'!$C$10) | H53: =CEILING(N(F53)*M53+L53,'Paramètres'!$C$12) | I53: =H53*(1+'Paramètres'!$C$11) | K53: Graphiste | L53: 0 | M53: =IFERROR(INDEX('Paramètres'!$C$17:$C$29,MATCH(K53,'Paramètres'!$B$17:$B$29,0)),0)
B54: 03.02 | C54: Journée de graphisme | D54: Journée de création (1 j/h) | E54: jour | F54: 8 | G54: =IF(F54="","",F54/'Paramètres'!$C$10) | H54: =CEILING(N(F54)*M54+L54,'Paramètres'!$C$12) | I54: =H54*(1+'Paramètres'!$C$11) | K54: Graphiste | L54: 0 | M54: =IFERROR(INDEX('Paramètres'!$C$17:$C$29,MATCH(K54,'Paramètres'!$B$17:$B$29,0)),0)
B55: 03.03 | C55: Flyer A5 / A4 | D55: Recto-verso, fichiers prêts à imprimer | E55: forfait | F55: 4 | G55: =IF(F55="","",F55/'Paramètres'!$C$10) | H55: =CEILING(N(F55)*M55+L55,'Paramètres'!$C$12) | I55: =H55*(1+'Paramètres'!$C$11) | K55: Graphiste | L55: 0 | M55: =IFERROR(INDEX('Paramètres'!$C$17:$C$29,MATCH(K55,'Paramètres'!$B$17:$B$29,0)),0)
B56: 03.04 | C56: Dépliant 3 volets | D56: Mise en page complète | E56: forfait | F56: 8 | G56: =IF(F56="","",F56/'Paramètres'!$C$10) | H56: =CEILING(N(F56)*M56+L56,'Paramètres'!$C$12) | I56: =H56*(1+'Paramètres'!$C$11) | K56: Graphiste | L56: 0 | M56: =IFERROR(INDEX('Paramètres'!$C$17:$C$29,MATCH(K56,'Paramètres'!$B$17:$B$29,0)),0)
B57: 03.05 | C57: Brochure 8 pages | D57: Conception + mise en page | E57: forfait | F57: 16 | G57: =IF(F57="","",F57/'Paramètres'!$C$10) | H57: =CEILING(N(F57)*M57+L57,'Paramètres'!$C$12) | I57: =H57*(1+'Paramètres'!$C$11) | K57: Graphiste | L57: 0 | M57: =IFERROR(INDEX('Paramètres'!$C$17:$C$29,MATCH(K57,'Paramètres'!$B$17:$B$29,0)),0)
B58: 03.06 | C58: Catalogue / brochure — par page | D58: Mise en page, au-delà de 8 pages | E58: page | F58: 1.5 | G58: =IF(F58="","",F58/'Paramètres'!$C$10) | H58: =CEILING(N(F58)*M58+L58,'Paramètres'!$C$12) | I58: =H58*(1+'Paramètres'!$C$11) | K58: Graphiste | L58: 0 | M58: =IFERROR(INDEX('Paramètres'!$C$17:$C$29,MATCH(K58,'Paramètres'!$B$17:$B$29,0)),0)
B59: 03.07 | C59: Affiche / poster | D59: Tout format | E59: forfait | F59: 4 | G59: =IF(F59="","",F59/'Paramètres'!$C$10) | H59: =CEILING(N(F59)*M59+L59,'Paramètres'!$C$12) | I59: =H59*(1+'Paramètres'!$C$11) | K59: Graphiste | L59: 0 | M59: =IFERROR(INDEX('Paramètres'!$C$17:$C$29,MATCH(K59,'Paramètres'!$B$17:$B$29,0)),0)
B60: 03.08 | C60: Roll-up / kakémono | D60: Format standard 85 × 200 cm | E60: forfait | F60: 4 | G60: =IF(F60="","",F60/'Paramètres'!$C$10) | H60: =CEILING(N(F60)*M60+L60,'Paramètres'!$C$12) | I60: =H60*(1+'Paramètres'!$C$11) | K60: Graphiste | L60: 0 | M60: =IFERROR(INDEX('Paramètres'!$C$17:$C$29,MATCH(K60,'Paramètres'!$B$17:$B$29,0)),0)
B61: 03.09 | C61: Bâche / banderole | D61: Grand format | E61: forfait | F61: 3 | G61: =IF(F61="","",F61/'Paramètres'!$C$10) | H61: =CEILING(N(F61)*M61+L61,'Paramètres'!$C$12) | I61: =H61*(1+'Paramètres'!$C$11) | K61: Graphiste | L61: 0 | M61: =IFERROR(INDEX('Paramètres'!$C$17:$C$29,MATCH(K61,'Paramètres'!$B$17:$B$29,0)),0)
B62: 03.10 | C62: Annonce presse / magazine | D62: Création + déclinaisons formats | E62: forfait | F62: 3 | G62: =IF(F62="","",F62/'Paramètres'!$C$10) | H62: =CEILING(N(F62)*M62+L62,'Paramètres'!$C$12) | I62: =H62*(1+'Paramètres'!$C$11) | K62: Graphiste | L62: 0 | M62: =IFERROR(INDEX('Paramètres'!$C$17:$C$29,MATCH(K62,'Paramètres'!$B$17:$B$29,0)),0)
B63: 03.11 | C63: Carton d'invitation | D63: Événement, portes ouvertes | E63: forfait | F63: 3 | G63: =IF(F63="","",F63/'Paramètres'!$C$10) | H63: =CEILING(N(F63)*M63+L63,'Paramètres'!$C$12) | I63: =H63*(1+'Paramètres'!$C$11) | K63: Graphiste | L63: 0 | M63: =IFERROR(INDEX('Paramètres'!$C$17:$C$29,MATCH(K63,'Paramètres'!$B$17:$B$29,0)),0)
B64: 03.12 | C64: Packaging / étiquette | D64: Création d'un design de packaging | E64: forfait | F64: 16 | G64: =IF(F64="","",F64/'Paramètres'!$C$10) | H64: =CEILING(N(F64)*M64+L64,'Paramètres'!$C$12) | I64: =H64*(1+'Paramètres'!$C$11) | K64: Graphiste | L64: 0 | M64: =IFERROR(INDEX('Paramètres'!$C$17:$C$29,MATCH(K64,'Paramètres'!$B$17:$B$29,0)),0)
B65: 03.13 | C65: Déclinaison / adaptation de format | D65: Adaptation d'un visuel existant | E65: forfait | F65: 1 | G65: =IF(F65="","",F65/'Paramètres'!$C$10) | H65: =CEILING(N(F65)*M65+L65,'Paramètres'!$C$12) | I65: =H65*(1+'Paramètres'!$C$11) | K65: Graphiste | L65: 0 | M65: =IFERROR(INDEX('Paramètres'!$C$17:$C$29,MATCH(K65,'Paramètres'!$B$17:$B$29,0)),0)
B67: 04 | C67: SIGNALÉTIQUE, SALONS & ÉVÉNEMENTIEL
B68: 04.01 | C68: Stand salon / foire | D68: Conception graphique du stand | E68: forfait | F68: 16 | G68: =IF(F68="","",F68/'Paramètres'!$C$10) | H68: =CEILING(N(F68)*M68+L68,'Paramètres'!$C$12) | I68: =H68*(1+'Paramètres'!$C$11) | K68: Graphiste | L68: 0 | M68: =IFERROR(INDEX('Paramètres'!$C$17:$C$29,MATCH(K68,'Paramètres'!$B$17:$B$29,0)),0)
B69: 04.02 | C69: Habillage véhicule | D69: Utilitaire ou voiture de service | E69: forfait | F69: 8 | G69: =IF(F69="","",F69/'Paramètres'!$C$10) | H69: =CEILING(N(F69)*M69+L69,'Paramètres'!$C$12) | I69: =H69*(1+'Paramètres'!$C$11) | K69: Graphiste | L69: 0 | M69: =IFERROR(INDEX('Paramètres'!$C$17:$C$29,MATCH(K69,'Paramètres'!$B$17:$B$29,0)),0)
B70: 04.03 | C70: Vitrine / enseigne | D70: Design de façade ou vitrophanie | E70: forfait | F70: 6 | G70: =IF(F70="","",F70/'Paramètres'!$C$10) | H70: =CEILING(N(F70)*M70+L70,'Paramètres'!$C$12) | I70: =H70*(1+'Paramètres'!$C$11) | K70: Graphiste | L70: 0 | M70: =IFERROR(INDEX('Paramètres'!$C$17:$C$29,MATCH(K70,'Paramètres'!$B$17:$B$29,0)),0)
B71: 04.04 | C71: Signalétique intérieure / showroom | D71: Panneaux, directionnel, PLV | E71: forfait | F71: 8 | G71: =IF(F71="","",F71/'Paramètres'!$C$10) | H71: =CEILING(N(F71)*M71+L71,'Paramètres'!$C$12) | I71: =H71*(1+'Paramètres'!$C$11) | K71: Graphiste | L71: 0 | M71: =IFERROR(INDEX('Paramètres'!$C$17:$C$29,MATCH(K71,'Paramètres'!$B$17:$B$29,0)),0)
B72: 04.05 | C72: PLV / présentoir | D72: Présentoir comptoir ou sol | E72: forfait | F72: 6 | G72: =IF(F72="","",F72/'Paramètres'!$C$10) | H72: =CEILING(N(F72)*M72+L72,'Paramètres'!$C$12) | I72: =H72*(1+'Paramètres'!$C$11) | K72: Graphiste | L72: 0 | M72: =IFERROR(INDEX('Paramètres'!$C$17:$C$29,MATCH(K72,'Paramètres'!$B$17:$B$29,0)),0)
B74: 05 | C74: ILLUSTRATION, 3D & INFOGRAPHIE
B75: 05.01 | C75: Illustration simple | D75: Pictogramme élaboré, dessin au trait | E75: forfait | F75: 3 | G75: =IF(F75="","",F75/'Paramètres'!$C$10) | H75: =CEILING(N(F75)*M75+L75,'Paramètres'!$C$12) | I75: =H75*(1+'Paramètres'!$C$11) | K75: Illustrateur | L75: 0 | M75: =IFERROR(INDEX('Paramètres'!$C$17:$C$29,MATCH(K75,'Paramètres'!$B$17:$B$29,0)),0)
B76: 05.02 | C76: Illustration détaillée | D76: Illustration couleur complexe | E76: forfait | F76: 10 | G76: =IF(F76="","",F76/'Paramètres'!$C$10) | H76: =CEILING(N(F76)*M76+L76,'Paramètres'!$C$12) | I76: =H76*(1+'Paramètres'!$C$11) | K76: Illustrateur | L76: 0 | M76: =IFERROR(INDEX('Paramètres'!$C$17:$C$29,MATCH(K76,'Paramètres'!$B$17:$B$29,0)),0)
B77: 05.03 | C77: Pack de 10 pictogrammes | D77: Set d'icônes cohérent | E77: forfait | F77: 8 | G77: =IF(F77="","",F77/'Paramètres'!$C$10) | H77: =CEILING(N(F77)*M77+L77,'Paramètres'!$C$12) | I77: =H77*(1+'Paramètres'!$C$11) | K77: Illustrateur | L77: 0 | M77: =IFERROR(INDEX('Paramètres'!$C$17:$C$29,MATCH(K77,'Paramètres'!$B$17:$B$29,0)),0)
B78: 05.04 | C78: Infographie | D78: Schéma, données, processus | E78: forfait | F78: 6 | G78: =IF(F78="","",F78/'Paramètres'!$C$10) | H78: =CEILING(N(F78)*M78+L78,'Paramètres'!$C$12) | I78: =H78*(1+'Paramètres'!$C$11) | K78: Graphiste | L78: 0 | M78: =IFERROR(INDEX('Paramètres'!$C$17:$C$29,MATCH(K78,'Paramètres'!$B$17:$B$29,0)),0)
B79: 05.05 | C79: Modélisation 3D & rendu | D79: Modèle 3D + 3 rendus photoréalistes | E79: forfait | F79: 16 | G79: =IF(F79="","",F79/'Paramètres'!$C$10) | H79: =CEILING(N(F79)*M79+L79,'Paramètres'!$C$12) | I79: =H79*(1+'Paramètres'!$C$11) | K79: Designer 3D | L79: 0 | M79: =IFERROR(INDEX('Paramètres'!$C$17:$C$29,MATCH(K79,'Paramètres'!$B$17:$B$29,0)),0)
B80: 05.06 | C80: Mockups / mises en situation | D80: 3 visuels de présentation | E80: forfait | F80: 2 | G80: =IF(F80="","",F80/'Paramètres'!$C$10) | H80: =CEILING(N(F80)*M80+L80,'Paramètres'!$C$12) | I80: =H80*(1+'Paramètres'!$C$11) | K80: Graphiste | L80: 0 | M80: =IFERROR(INDEX('Paramètres'!$C$17:$C$29,MATCH(K80,'Paramètres'!$B$17:$B$29,0)),0)
B82: 06 | C82: PHOTOGRAPHIE
B83: 06.01 | C83: Shooting photo — demi-journée | D83: 4 h sur site, 20 photos retouchées, matériel inclus | E83: demi-journée | F83: 4 | G83: =IF(F83="","",F83/'Paramètres'!$C$10) | H83: =CEILING(N(F83)*M83+L83,'Paramètres'!$C$12) | I83: =H83*(1+'Paramètres'!$C$11) | K83: Photographe | L83: 50 | M83: =IFERROR(INDEX('Paramètres'!$C$17:$C$29,MATCH(K83,'Paramètres'!$B$17:$B$29,0)),0)
B84: 06.02 | C84: Shooting photo — journée | D84: 8 h sur site, 40 photos retouchées, matériel inclus | E84: jour | F84: 8 | G84: =IF(F84="","",F84/'Paramètres'!$C$10) | H84: =CEILING(N(F84)*M84+L84,'Paramètres'!$C$12) | I84: =H84*(1+'Paramètres'!$C$11) | K84: Photographe | L84: 80 | M84: =IFERROR(INDEX('Paramètres'!$C$17:$C$29,MATCH(K84,'Paramètres'!$B$17:$B$29,0)),0)
B85: 06.03 | C85: Packshot produit — par photo | D85: Fond blanc ou mise en scène | E85: photo | F85: 0.5 | G85: =IF(F85="","",F85/'Paramètres'!$C$10) | H85: =CEILING(N(F85)*M85+L85,'Paramètres'!$C$12) | I85: =H85*(1+'Paramètres'!$C$11) | K85: Photographe | L85: 0 | M85: =IFERROR(INDEX('Paramètres'!$C$17:$C$29,MATCH(K85,'Paramètres'!$B$17:$B$29,0)),0)
B86: 06.04 | C86: Portraits corporate | D86: Équipe / dirigeants, jusqu'à 10 personnes | E86: forfait | F86: 4 | G86: =IF(F86="","",F86/'Paramètres'!$C$10) | H86: =CEILING(N(F86)*M86+L86,'Paramètres'!$C$12) | I86: =H86*(1+'Paramètres'!$C$11) | K86: Photographe | L86: 50 | M86: =IFERROR(INDEX('Paramètres'!$C$17:$C$29,MATCH(K86,'Paramètres'!$B$17:$B$29,0)),0)
B87: 06.05 | C87: Reportage événement / chantier | D87: Couverture 4 h, sélection retouchée | E87: forfait | F87: 5 | G87: =IF(F87="","",F87/'Paramètres'!$C$10) | H87: =CEILING(N(F87)*M87+L87,'Paramètres'!$C$12) | I87: =H87*(1+'Paramètres'!$C$11) | K87: Photographe | L87: 50 | M87: =IFERROR(INDEX('Paramètres'!$C$17:$C$29,MATCH(K87,'Paramètres'!$B$17:$B$29,0)),0)
B88: 06.06 | C88: Photo aérienne par drone | D88: Demi-journée, pilote certifié | E88: demi-journée | F88: 4 | G88: =IF(F88="","",F88/'Paramètres'!$C$10) | H88: =CEILING(N(F88)*M88+L88,'Paramètres'!$C$12) | I88: =H88*(1+'Paramètres'!$C$11) | K88: Pilote drone | L88: 150 | M88: =IFERROR(INDEX('Paramètres'!$C$17:$C$29,MATCH(K88,'Paramètres'!$B$17:$B$29,0)),0)
B89: 06.07 | C89: Retouche avancée — par photo | D89: Détourage, montage, retouche poussée | E89: photo | F89: 0.5 | G89: =IF(F89="","",F89/'Paramètres'!$C$10) | H89: =CEILING(N(F89)*M89+L89,'Paramètres'!$C$12) | I89: =H89*(1+'Paramètres'!$C$11) | K89: Photographe | L89: 0 | M89: =IFERROR(INDEX('Paramètres'!$C$17:$C$29,MATCH(K89,'Paramètres'!$B$17:$B$29,0)),0)
B91: 07 | C91: VIDÉO & MOTION DESIGN
B92: 07.01 | C92: Tournage — demi-journée | D92: Vidéaste + matériel (caméra, son, lumière) | E92: demi-journée | F92: 4 | G92: =IF(F92="","",F92/'Paramètres'!$C$10) | H92: =CEILING(N(F92)*M92+L92,'Paramètres'!$C$12) | I92: =H92*(1+'Paramètres'!$C$11) | K92: Vidéaste | L92: 100 | M92: =IFERROR(INDEX('Paramètres'!$C$17:$C$29,MATCH(K92,'Paramètres'!$B$17:$B$29,0)),0)
B93: 07.02 | C93: Tournage — journée | D93: Vidéaste + matériel (caméra, son, lumière) | E93: jour | F93: 8 | G93: =IF(F93="","",F93/'Paramètres'!$C$10) | H93: =CEILING(N(F93)*M93+L93,'Paramètres'!$C$12) | I93: =H93*(1+'Paramètres'!$C$11) | K93: Vidéaste | L93: 150 | M93: =IFERROR(INDEX('Paramètres'!$C$17:$C$29,MATCH(K93,'Paramètres'!$B$17:$B$29,0)),0)
B94: 07.03 | C94: Prises de vue drone | D94: Demi-journée, pilote certifié | E94: demi-journée | F94: 4 | G94: =IF(F94="","",F94/'Paramètres'!$C$10) | H94: =CEILING(N(F94)*M94+L94,'Paramètres'!$C$12) | I94: =H94*(1+'Paramètres'!$C$11) | K94: Pilote drone | L94: 150 | M94: =IFERROR(INDEX('Paramètres'!$C$17:$C$29,MATCH(K94,'Paramètres'!$B$17:$B$29,0)),0)
B95: 07.04 | C95: Heure de montage | D95: Montage, étalonnage, mixage | E95: heure | F95: 1 | G95: =IF(F95="","",F95/'Paramètres'!$C$10) | H95: =CEILING(N(F95)*M95+L95,'Paramètres'!$C$12) | I95: =H95*(1+'Paramètres'!$C$11) | K95: Monteur / motion designer | L95: 0 | M95: =IFERROR(INDEX('Paramètres'!$C$17:$C$29,MATCH(K95,'Paramètres'!$B$17:$B$29,0)),0)
B96: 07.05 | C96: Film de présentation 1–2 min | D96: Montage complet, 2 allers-retours | E96: forfait | F96: 16 | G96: =IF(F96="","",F96/'Paramètres'!$C$10) | H96: =CEILING(N(F96)*M96+L96,'Paramètres'!$C$12) | I96: =H96*(1+'Paramètres'!$C$11) | K96: Monteur / motion designer | L96: 0 | M96: =IFERROR(INDEX('Paramètres'!$C$17:$C$29,MATCH(K96,'Paramètres'!$B$17:$B$29,0)),0)
B97: 07.06 | C97: Vidéo témoignage client | D97: Interview montée, 1–2 min | E97: forfait | F97: 8 | G97: =IF(F97="","",F97/'Paramètres'!$C$10) | H97: =CEILING(N(F97)*M97+L97,'Paramètres'!$C$12) | I97: =H97*(1+'Paramètres'!$C$11) | K97: Monteur / motion designer | L97: 0 | M97: =IFERROR(INDEX('Paramètres'!$C$17:$C$29,MATCH(K97,'Paramètres'!$B$17:$B$29,0)),0)
B98: 07.07 | C98: Réel / short réseaux sociaux | D98: Format vertical ≤ 60 s | E98: forfait | F98: 3 | G98: =IF(F98="","",F98/'Paramètres'!$C$10) | H98: =CEILING(N(F98)*M98+L98,'Paramètres'!$C$12) | I98: =H98*(1+'Paramètres'!$C$11) | K98: Monteur / motion designer | L98: 0 | M98: =IFERROR(INDEX('Paramètres'!$C$17:$C$29,MATCH(K98,'Paramètres'!$B$17:$B$29,0)),0)
B99: 07.08 | C99: Motion design 30 s | D99: Animation 2D, script et storyboard inclus | E99: forfait | F99: 24 | G99: =IF(F99="","",F99/'Paramètres'!$C$10) | H99: =CEILING(N(F99)*M99+L99,'Paramètres'!$C$12) | I99: =H99*(1+'Paramètres'!$C$11) | K99: Monteur / motion designer | L99: 0 | M99: =IFERROR(INDEX('Paramètres'!$C$17:$C$29,MATCH(K99,'Paramètres'!$B$17:$B$29,0)),0)
B100: 07.09 | C100: Animation de logo | D100: Logo animé (intro / outro) | E100: forfait | F100: 6 | G100: =IF(F100="","",F100/'Paramètres'!$C$10) | H100: =CEILING(N(F100)*M100+L100,'Paramètres'!$C$12) | I100: =H100*(1+'Paramètres'!$C$11) | K100: Monteur / motion designer | L100: 0 | M100: =IFERROR(INDEX('Paramètres'!$C$17:$C$29,MATCH(K100,'Paramètres'!$B$17:$B$29,0)),0)
B101: 07.10 | C101: Animation 3D | D101: Visualisation produit / installation | E101: forfait | F101: 24 | G101: =IF(F101="","",F101/'Paramètres'!$C$10) | H101: =CEILING(N(F101)*M101+L101,'Paramètres'!$C$12) | I101: =H101*(1+'Paramètres'!$C$11) | K101: Designer 3D | L101: 0 | M101: =IFERROR(INDEX('Paramètres'!$C$17:$C$29,MATCH(K101,'Paramètres'!$B$17:$B$29,0)),0)
B102: 07.11 | C102: Sous-titrage | D102: Par vidéo, 1 langue | E102: forfait | F102: 2 | G102: =IF(F102="","",F102/'Paramètres'!$C$10) | H102: =CEILING(N(F102)*M102+L102,'Paramètres'!$C$12) | I102: =H102*(1+'Paramètres'!$C$11) | K102: Monteur / motion designer | L102: 0 | M102: =IFERROR(INDEX('Paramètres'!$C$17:$C$29,MATCH(K102,'Paramètres'!$B$17:$B$29,0)),0)
B103: 07.12 | C103: Voix off professionnelle | D103: Comédien voix, 1 langue | E103: forfait | F103: 1 | G103: =IF(F103="","",F103/'Paramètres'!$C$10) | H103: =CEILING(N(F103)*M103+L103,'Paramètres'!$C$12) | I103: =H103*(1+'Paramètres'!$C$11) | K103: Monteur / motion designer | L103: 150 | M103: =IFERROR(INDEX('Paramètres'!$C$17:$C$29,MATCH(K103,'Paramètres'!$B$17:$B$29,0)),0)
B104: 07.13 | C104: Musique sous licence | D104: Droits d'utilisation web | E104: forfait | G104: =IF(F104="","",F104/'Paramètres'!$C$10) | H104: =CEILING(N(F104)*M104+L104,'Paramètres'!$C$12) | I104: =H104*(1+'Paramètres'!$C$11) | K104: Monteur / motion designer | L104: 50 | M104: =IFERROR(INDEX('Paramètres'!$C$17:$C$29,MATCH(K104,'Paramètres'!$B$17:$B$29,0)),0)
B106: 08 | C106: WEB & DIGITAL
B107: 08.01 | C107: Webdesign UI/UX — par page | D107: Maquette desktop + mobile | E107: page | F107: 6 | G107: =IF(F107="","",F107/'Paramètres'!$C$10) | H107: =CEILING(N(F107)*M107+L107,'Paramètres'!$C$12) | I107: =H107*(1+'Paramètres'!$C$11) | K107: Webdesigner UI/UX | L107: 0 | M107: =IFERROR(INDEX('Paramètres'!$C$17:$C$29,MATCH(K107,'Paramètres'!$B$17:$B$29,0)),0)
B108: 08.02 | C108: Site vitrine (5–7 pages) | D108: Design + développement WordPress, responsive | E108: forfait | F108: 48 | G108: =IF(F108="","",F108/'Paramètres'!$C$10) | H108: =CEILING(N(F108)*M108+L108,'Paramètres'!$C$12) | I108: =H108*(1+'Paramètres'!$C$11) | K108: Développeur web | L108: 0 | M108: =IFERROR(INDEX('Paramètres'!$C$17:$C$29,MATCH(K108,'Paramètres'!$B$17:$B$29,0)),0)
B109: 08.03 | C109: Site e-commerce | D109: Boutique en ligne, paiement, jusqu'à 50 produits | E109: forfait | F109: 100 | G109: =IF(F109="","",F109/'Paramètres'!$C$10) | H109: =CEILING(N(F109)*M109+L109,'Paramètres'!$C$12) | I109: =H109*(1+'Paramètres'!$C$11) | K109: Développeur web | L109: 0 | M109: =IFERROR(INDEX('Paramètres'!$C$17:$C$29,MATCH(K109,'Paramètres'!$B$17:$B$29,0)),0)
B110: 08.04 | C110: Landing page | D110: Page promotionnelle / campagne | E110: forfait | F110: 12 | G110: =IF(F110="","",F110/'Paramètres'!$C$10) | H110: =CEILING(N(F110)*M110+L110,'Paramètres'!$C$12) | I110: =H110*(1+'Paramètres'!$C$11) | K110: Développeur web | L110: 0 | M110: =IFERROR(INDEX('Paramètres'!$C$17:$C$29,MATCH(K110,'Paramètres'!$B$17:$B$29,0)),0)
B111: 08.05 | C111: Rédaction web — par page | D111: Textes optimisés SEO | E111: page | F111: 2 | G111: =IF(F111="","",F111/'Paramètres'!$C$10) | H111: =CEILING(N(F111)*M111+L111,'Paramètres'!$C$12) | I111: =H111*(1+'Paramètres'!$C$11) | K111: Rédacteur / copywriter | L111: 0 | M111: =IFERROR(INDEX('Paramètres'!$C$17:$C$29,MATCH(K111,'Paramètres'!$B$17:$B$29,0)),0)
B112: 08.06 | C112: Audit & optimisation SEO | D112: Analyse technique + recommandations | E112: forfait | F112: 10 | G112: =IF(F112="","",F112/'Paramètres'!$C$10) | H112: =CEILING(N(F112)*M112+L112,'Paramètres'!$C$12) | I112: =H112*(1+'Paramètres'!$C$11) | K112: Développeur web | L112: 0 | M112: =IFERROR(INDEX('Paramètres'!$C$17:$C$29,MATCH(K112,'Paramètres'!$B$17:$B$29,0)),0)
B113: 08.07 | C113: Template newsletter | D113: Modèle e-mailing responsive | E113: forfait | F113: 6 | G113: =IF(F113="","",F113/'Paramètres'!$C$10) | H113: =CEILING(N(F113)*M113+L113,'Paramètres'!$C$12) | I113: =H113*(1+'Paramètres'!$C$11) | K113: Webdesigner UI/UX | L113: 0 | M113: =IFERROR(INDEX('Paramètres'!$C$17:$C$29,MATCH(K113,'Paramètres'!$B$17:$B$29,0)),0)
B114: 08.08 | C114: Formation back-office | D114: Prise en main du site (2 h) | E114: forfait | F114: 2 | G114: =IF(F114="","",F114/'Paramètres'!$C$10) | H114: =CEILING(N(F114)*M114+L114,'Paramètres'!$C$12) | I114: =H114*(1+'Paramètres'!$C$11) | K114: Développeur web | L114: 0 | M114: =IFERROR(INDEX('Paramètres'!$C$17:$C$29,MATCH(K114,'Paramètres'!$B$17:$B$29,0)),0)
...

Sheet Paramètres
B2: PARAMÈTRES — usage interne
B3: Modifiez uniquement les cellules en bleu sur fond jaune. La price list se met à jour automatiquement.
B5: Nom de l'agence | C5: [NOM DE VOTRE AGENCE]
B6: Coordonnées agence | C6: [adresse · téléphone · e-mail · site web · n° TVA]
B7: Client | C7: Démarches SRL — concessionnaire Helicave
B8: Date de la price list | C8: 46288
B9: Validité de l'offre (jours) | C9: 90
B10: Heures par jour de travail (1 j/h) | C10: 8
B11: TVA | C11: 0.21 | D11: TVA belge 21 %. Mettre 0 % si non applicable.
B12: Arrondi des prix (€) | C12: 5 | D12: Les prix calculés sont arrondis au multiple supérieur (ex. 5 €).
B15: TAUX HORAIRES PAR PROFIL (HT)
B16: Profil | C16: Taux horaire HT | D16: Taux journalier HT
B17: Directeur artistique | C17: 85 | D17: =C17*$C$10
B18: Chef de projet | C18: 70 | D18: =C18*$C$10
B19: Graphiste | C19: 65 | D19: =C19*$C$10
B20: Illustrateur | C20: 65 | D20: =C20*$C$10
B21: Designer 3D | C21: 75 | D21: =C21*$C$10
B22: Photographe | C22: 70 | D22: =C22*$C$10
B23: Vidéaste | C23: 75 | D23: =C23*$C$10
B24: Monteur / motion designer | C24: 70 | D24: =C24*$C$10
B25: Pilote drone | C25: 85 | D25: =C25*$C$10
B26: Webdesigner UI/UX | C26: 70 | D26: =C26*$C$10
B27: Développeur web | C27: 70 | D27: =C27*$C$10
B28: Community manager | C28: 55 | D28: =C28*$C$10
B29: Rédacteur / copywriter | C29: 55 | D29: =C29*$C$10
B31: Taux indicatifs (fourchette moyenne d'une agence de communication en Belgique) — à remplacer par vos tarifs réels.
